[{"key":"man_made","tags":[{"value":"cellar_entrance","count":10}],"count":10},{"key":"cellar:use","tags":[{"value":"icehouse","count":1},{"value":"prison","count":1},{"value":"wine","count":1},{"value":"storage","count":1}],"count":4},{"key":"historic","tags":[{"value":"yes","count":1},{"value":"archaeological_site","count":1},{"value":"ruins","count":1}],"count":3},{"key":"access","tags":[{"value":"yes","count":1},{"value":"no","count":1}],"count":2},{"key":"cellar:type","tags":[{"value":"ground","count":1},{"value":"brick","count":1}],"count":2},{"key":"tourism","tags":[{"value":"attraction","count":1}],"count":1},{"key":"barrier","tags":[{"value":"gate","count":1}],"count":1},{"key":"direction","tags":[{"value":"W","count":1}],"count":1},{"key":"fee","tags":[{"value":"no","count":1}],"count":1},{"key":"natural","tags":[{"value":"cave_entrance","count":1}],"count":1},{"key":"ruins","tags":[{"value":"yes","count":1}],"count":1}]