[{"key":"shop","tags":[{"value":"fireplace","count":134}],"count":134},{"key":"entrance","tags":[{"value":"yes","count":5}],"count":5},{"key":"brand","tags":[{"value":"Aäsgard","count":1},{"value":"Hase","count":1},{"value":"Jotul","count":1},{"value":"Scan","count":1},{"value":"Atra","count":1},{"value":"Faber","count":1},{"value":"Ignisial","count":1},{"value":"Hoben","count":1},{"value":"Cheminées Philippe","count":1}],"count":4},{"key":"wheelchair","tags":[{"value":"no","count":2},{"value":"limited","count":1}],"count":3},{"key":"craft","tags":[{"value":"hvac","count":1}],"count":1},{"key":"owner","tags":[{"value":"Novadev","count":1}],"count":1},{"key":"payment:credit_cards","tags":[{"value":"yes","count":1}],"count":1},{"key":"roof:shape","tags":[{"value":"flat","count":1}],"count":1}]