[{"key":"man_made","tags":[{"value":"tank","count":504}],"count":504},{"key":"tank:type","tags":[{"value":"unknown","count":113}],"count":113},{"key":"height","tags":[{"value":"9","count":17},{"value":"7","count":6},{"value":"4","count":1},{"value":"5","count":1},{"value":"10","count":1},{"value":"17","count":1}],"count":27},{"key":"roof:material","tags":[{"value":"metal","count":27}],"count":27},{"key":"content","tags":[{"value":"slurry","count":9},{"value":"wastewater","count":8},{"value":"fuel","count":4},{"value":"gas","count":3},{"value":"oil","count":2}],"count":26},{"key":"operator","tags":[{"value":"DB Energie GmbH","count":8},{"value":"vlexx GmbH","count":2},{"value":"Silo Nordzucker AG","count":1}],"count":11},{"key":"reservoir_type","tags":[{"value":"sewage","count":8},{"value":"digestion_tower","count":2}],"count":10},{"key":"landuse","tags":[{"value":"reservoir","count":8}],"count":8},{"key":"fuel","tags":[{"value":"diesel","count":3},{"value":"ad_blue","count":1}],"count":4},{"key":"historic","tags":[{"value":"tank","count":2},{"value":"technical_monument","count":1}],"count":3},{"key":"capacity","tags":[{"value":"100000","count":2},{"value":"20000","count":1}],"count":3},{"key":"min_height","tags":[{"value":"4","count":1}],"count":1}]