[{"key":"amenity","tags":[{"value":"public_bookcase","count":977}],"count":977},{"key":"public_bookcase:type","tags":[{"value":"reading_box","count":125},{"value":"phone_box","count":50},{"value":"wooden_cabinet","count":44},{"value":"metal_cabinet","count":15},{"value":"shelter","count":10},{"value":"sculpture","count":9},{"value":"shelf","count":8},{"value":"post_box","count":3},{"value":"glass_cabinet","count":2},{"value":"phonebox","count":1},{"value":"cabinet","count":1},{"value":"refrigerator","count":1},{"value":"fridge","count":1},{"value":"boîte_à_livre","count":1},{"value":"wooden_box","count":1}],"count":272},{"key":"operator","tags":[{"value":"Commission de quartier","count":30},{"value":"Ville de Bayonne","count":6},{"value":"Chantepie Initiatives","count":6},{"value":"Touraine propre","count":6},{"value":"3 Chêne Culture","count":5},{"value":"Villenave-d'Ornon","count":5},{"value":"Ville de Rouen","count":5},{"value":"Bibliothèque municipale","count":5},{"value":"Mairie de Montrouge","count":4},{"value":"Wittenheim","count":3},{"value":"Le Salon de Lecture, Le Local","count":3},{"value":"Mairie de Saint-Paul-lès-Dax","count":3},{"value":"Commune de Champagnole","count":3},{"value":"Fonds Decitre","count":3},{"value":"Bibliothèque de Geneston","count":2},{"value":"Illzach","count":2},{"value":"Mairie d'hondeghem","count":2},{"value":"Amiens Métropole","count":2},{"value":"Lions Club Bordeaux La Fayette","count":2},{"value":"Association Carterie Chateaulin","count":2},{"value":"Mairie de L'Haÿ les Roses","count":2},{"value":"Caluire-et-Cuire","count":2},{"value":"Mairie","count":2},{"value":"Ville de Saint-Jean-de-Moirans","count":1},{"value":"Conseil de quartier Mutualité Préfecture Moncey","count":1},{"value":"Lions Club Vaucluse","count":1},{"value":"Médiathèque intercommunale des Vosges du Sud","count":1},{"value":"SavoieRécup","count":1},{"value":"Art Book Collectif Marseille","count":1},{"value":"Association \"Livre Ensemble\"","count":1},{"value":"Le Gasseau","count":1},{"value":"Lions Club Romorantin Sologne","count":1},{"value":"Conseil de quartier d'Issy les Moulineaux","count":1},{"value":"Lions Club Fréjus Roquebrune en Provence","count":1},{"value":"Pop'Art café","count":1},{"value":"Mairie de Chalon-sur-Saône","count":1},{"value":"Association des résidents de la Guingette","count":1},{"value":"Ville Olivet","count":1},{"value":"Salon de Lecture, Le Local, GEM","count":1},{"value":"Particulier ?","count":1},{"value":"Centre social Equinoxe","count":1},{"value":"Particulier","count":1},{"value":"Mairie de Betton","count":1},{"value":"Jeune Chambre Économique de Laval","count":1},{"value":"Mairie de Pau","count":1},{"value":"Des trucs avec les gens","count":1},{"value":"savoie-récup","count":1},{"value":"Le conseil municipal enfants de Les Marches","count":1},{"value":"Municipalité","count":1},{"value":"Lions Club Mulhouse Haute Alsace","count":1},{"value":"Boîte à Lire","count":1},{"value":"Centre social et culturel du Parmelan","count":1},{"value":"private","count":1},{"value":"Rotary Club de Sanary Bandol Ollioules","count":1},{"value":"Les Artistes autour du Puits","count":1},{"value":"Bibliothèque de la Ville-ès-Nonais","count":1},{"value":"Bibliothèque de laVille Es Nonais","count":1},{"value":"Salsa Familia Part'âges","count":1},{"value":"Conseil Municipal des Jeunes de Brive","count":1},{"value":"Ville d'Albi","count":1},{"value":"Amiens métropole","count":1},{"value":"Mairie de Romillé","count":1},{"value":"Café du Square","count":1},{"value":"Cherbourg en Cotentin","count":1},{"value":"3 Chêne-Culture","count":1},{"value":"Conseil des Jeunes d’Alfortville","count":1},{"value":"Lions Club Givet","count":1},{"value":"Lions Club Gisors-Templier","count":1},{"value":"particulier","count":1},{"value":"Bibliothèque Municipale de Nailloux","count":1},{"value":"Médiathèque municipale","count":1},{"value":"Mairie de Saint-Clément de Rivière","count":1},{"value":"Ville de La Baule Escoublac","count":1},{"value":"Conseil municipal des jeunes","count":1},{"value":"Bibliothèque municipale de Nailloux","count":1},{"value":"Mairie de Lognes","count":1},{"value":"Maison Pour Tous - Salle des Rancy","count":1},{"value":"Mairie de Luçon","count":1},{"value":"Mairie de Bordeaux","count":1},{"value":"Association L'arbre à livres","count":1},{"value":"Médiathèque Ernée","count":1},{"value":"École Harouys","count":1},{"value":"Association Littératures Européennes Cognac","count":1},{"value":"CCABV","count":1},{"value":"Lions Clubs","count":1},{"value":"collectif","count":1},{"value":"Vival","count":1},{"value":"buvette \"Au Calme\"","count":1},{"value":"Biocoop","count":1},{"value":"Conseil participatif Manufactures","count":1},{"value":"Comité de quartier Ouest-Nord de Cachan","count":1},{"value":"Comité de quartier du Coteau (Cachan)","count":1},{"value":"Comité de quartier de la Plaine (Cachan)","count":1},{"value":"CHRU","count":1},{"value":"Bibliothèque Centrale de Cachan","count":1},{"value":"Centre socioculturel Cousté","count":1}],"count":178},{"key":"capacity","tags":[{"value":"40","count":32},{"value":"30","count":10},{"value":"100","count":9},{"value":"50","count":8},{"value":"20","count":7},{"value":"60","count":6},{"value":"80","count":4},{"value":"10","count":2},{"value":"200","count":2},{"value":"150","count":2},{"value":"25","count":1},{"value":"44000","count":1},{"value":"250","count":1},{"value":"500","count":1},{"value":"15","count":1},{"value":"16","count":1},{"value":"1000","count":1}],"count":89},{"key":"description","tags":[{"value":"Système d'échange libre de livres","count":4},{"value":"Boite à livres","count":2},{"value":"Boîte à lire pour échanger des livres gratuitement et librement.","count":2},{"value":"bevind zich in de bibliotheek","count":1},{"value":"Située à côté de l'aire de jeu, 2 petites boites dans 2 tronc d'arbres. Celle-ci concerne les livres (roman) pour adultes.","count":1},{"value":"Située à côté de l'aire de jeu, 2 boîtes à livres dans des troncs. Celle-ci concerne les livres pour enfants.","count":1},{"value":"Système de « livres voyageurs » : livres en acces libre","count":1},{"value":"Cultivons le goût de lire. Boîte à livre livrée par le Lions Club.","count":1},{"value":"frigo","count":1},{"value":"Microbibliothèque avec 3 catégories: 3-6 ans, 7-10 ans, Ados","count":1},{"value":"Donnez les livres que vous ne lisez plus, prenez les livres que vous voulez lire. Bibliothèque gratuite autogérée.","count":1},{"value":"Venez déposer les livres que vous ne lisez plus, et emprunter de nouveaux. Bibliothèque partagée autogérée.","count":1},{"value":"Venez déposer les livres que vous ne lisez plus et en emprunter de nouveaux.","count":1},{"value":"Girafes","count":1},{"value":"Boite en forme de champignon. Il faut faire tourner le compartiment intérieur afin d'accéder à tous les livres.","count":1},{"value":"Etagère située à l'extérieur sous un corridor à gauche de l'entrée du 17 de la rue. En dessus des arceaux à vélo.","count":1},{"value":"Boite accessible depuis la rue Saint-Antoine. Fermée par 2 portes sans clé.","count":1},{"value":"Boite en acier de couleur bleu située à l'entrée du jardin public.","count":1},{"value":"librement accessible dans l'enceinte d'une résidence hlm","count":1},{"value":"Boite située sur le virage, des vitres protègent les livres des intempéries.","count":1},{"value":"Boite fixée sur le mur de la rampe d'accès à l'égilse Saint-Luc.","count":1},{"value":"La boîte à livres est un dispositif d'échanges gratuits de livres entre particuliers; aucune formalité, aucune obligation, pas d'inscription et pas frais.","count":1},{"value":"Boite en bois située à droite du CCAS sur le trottoir. Au 2019-02-12, il manque la porte de gauche.","count":1},{"value":"Vide lors de la visite.","count":1},{"value":"Boîte à livres installé sur le quai de l'arrêt de tram.","count":1},{"value":"Zone où l'on laisse et prend des livres gratuitement.","count":1},{"value":"'boitadon' à côté également. Accepte le 'recylivre'.","count":1},{"value":"Boite en bois située à l'intérieur du Parc de Marliave.","count":1},{"value":"Simple étagère","count":1},{"value":"Cercle des amateurs de Lecture de la médiathèque l'Ellipse. 22/09/2018","count":1},{"value":"Joli endroit où l'on peut lire, prendre un livre, ou en déposer... Il y a aussi des bandes dessinés, quelques DVDs.","count":1},{"value":"Cette boite est un gros pot de fleur rouge renversé maintenu en hauteur par 3 piquets. Les livres sont disposés de façon circulaire sur une étagère à l'intérieur du pot. Cette boite à livre n'est absolument pas accessible en fauteuil roulant.","count":1},{"value":"Boite à livre très colorée surmontée par une sculpture représentant une cigogne et son nid. La boite est située en hauteur sur un muret, ce qui peut la rendre difficile d'accès en fauteuil roulant.","count":1},{"value":"Jolie boîte en boite peinte par les élèves de l'école Harouys","count":1},{"value":"20€ l'adhésion","count":1},{"value":"Une boîte où déposer ses livres en trop et en trouver d'autres.","count":1},{"value":"Un réfrigérateur reconverti en boîte à livres...","count":1},{"value":"La boite à livre se trouve dans une sculpture en forme d’arbre près du chemin","count":1},{"value":"Étagère située près de la piste cyclable et du panneau d'affichage.","count":1},{"value":"Immense étagère à l'intérieur en face du Barathym. Les horaires dépendent des horaires du patio.","count":1},{"value":"La boîte à livre se trouve sur le muret donnant sur la rue","count":1},{"value":"Armoire de partage / échange d'épicerie sèche, vaiselle, hygiène, textiles, produits culturels (dont livres), jouets.","count":1},{"value":"La boite à livre se trouve en extérieur contre le mur de la MDH. Elle a été fabriqué par des producteurs locaux, une information cite les producteurs ainsi que les essences utilisées.","count":1},{"value":"La boite est accrochée au mur du local à poubelle à l'entrée de la copropriété des Florentines. La boite est une étagère en bois.","count":1},{"value":"Étagère en bois fermée par une porte. Elle est située sur la place Charles de Gaulle.","count":1},{"value":"Sculpture en forme d'arbre réalisée en carton. Les livres sont posés dans les interstices.","count":1},{"value":"Bac servant de boîte à livres à l'intérieur de la bibliothèque Centrale.","count":1}],"count":52},{"key":"website","tags":[{"value":"http://www.3chene-culture.ch/?page_id=676","count":6},{"value":"http://chantepie-initiatives.fr","count":6},{"value":"www.lelocal.co","count":4},{"value":"https://fonds.decitre.org/nos-actions-innovantes/boites-a-lire/","count":3},{"value":"https://polecultureldenailloux.jimdo.com/page-d-accueil/biblioth%C3%A8que-municipale/le-livre-vagabond/","count":2},{"value":"http://www.lions-france.org","count":2},{"value":"https://www.dissay.fr/uploads/ss3iCalendar/docs/notice.pdf","count":2},{"value":"https://metz.fr/lieux/lieu-3933.php","count":1},{"value":"http://www.artbookcollectif.marsnet.org/spip/","count":1},{"value":"http://www.mairie4.lyon.fr/actualite/conseils-de-quartier/apicq-la-boite-a-lire-arrive-sur-la-place-guichard-3eme-.html","count":1},{"value":"http://mediatheque-digne.fr/","count":1},{"value":"http://www.pessac.fr/annuaire/boite-livres-parc-fontaudin.html","count":1},{"value":"https://metz.fr/lieux/lieu-3934.php","count":1},{"value":"https://www.nanterre.fr/1566-maison-de-la-musique-mediatheque-musicale.htm","count":1},{"value":"http://www.olivet.fr/actualites/culture/les-livres-liberte-458.html?article=1374","count":1},{"value":"https://bibliolezat.wordpress.com/","count":1},{"value":"http://www.bibliotheque.toulouse.fr/boite_a_lire_place_legion_d_honneur.html","count":1},{"value":"http://lions-frances.org/","count":1},{"value":"http://www.psbangers.fr","count":1},{"value":"http://www.mairie-rueilmalmaison.fr/actualit%C3%A9s/th%C3%A8mes/culture-tourisme/lancement-de-%C2%AB-livres-en-libert%C3%A9","count":1},{"value":"https://www.facebook.com/LaCabaneALivres/","count":1},{"value":"https://www.ville-sannois.fr/content/une-boite-livres-la-gare-de-sannois","count":1},{"value":"http://lions-france.org","count":1},{"value":"https://litteratures-europeennes.com/actions-culturelles/bibliotheque-europeenne/","count":1},{"value":"https://www.boite-a-lire.com/","count":1},{"value":"https://www.facebook.com/boitealivresportboyer/","count":1}],"count":44},{"key":"lit","tags":[{"value":"no","count":38},{"value":"yes","count":6}],"count":44},{"key":"mapillary","tags":[{"value":"6gGLl2S18AlHi27WK0ZvWw","count":2},{"value":"VHcuMMgx2ZrIy3nngIt43w","count":1},{"value":"w6C_bz7jFWf8R4JggFLFHQ","count":1},{"value":"yKsy4sE9xO3UioLjQqyi9A","count":1},{"value":"vszNOhCiRMm0JRwo7CR97A","count":1},{"value":"ZjJEPF0BGQbuhz_JU5ASmQ","count":1},{"value":"x13IOLrGIaDgBfA15GmJyg","count":1},{"value":"OS1GgHCw1991F018OCFq8w","count":1},{"value":"KdMhqwOOKwyLazidrgXagQ","count":1},{"value":"1Vu89LcE6OgRAArajPG0Lg","count":1},{"value":"a6BCfhx_hC3DmumcnQjQWQ","count":1},{"value":"csjUWMK3jWqsWPqGB9f66Q","count":1},{"value":"ySpyD2FRYw-RIZtKDg1CGA","count":1},{"value":"THGoMGAAxk0WbVnpYTKF0A","count":1},{"value":"PoMmv5vhWbEUXfB40uL-QA","count":1},{"value":"WB0fIku7qgk0BLqhUNmAEA","count":1},{"value":"FpVdFaAxvbhVKLEOjrNItg","count":1},{"value":"_zwi8e6-HLuMyoscWrUgAA","count":1},{"value":"uuFtuSNJhuVMwDelju8WAw","count":1},{"value":"H2WLlMt1cs6GOraMJnpF2w","count":1},{"value":"qDlvWAIn-9HIm9ERxp-RAw","count":1},{"value":"O9Enl31GfXyhWkLaAkahLg","count":1},{"value":"MEtoy91aKsGHuNMXn7oiOA","count":1},{"value":"MALUheWhrjgiKWENnTOpnw","count":1},{"value":"KQJ9oU9L6HTPsy_-LCrhXA","count":1},{"value":"qwreNWsdbgfKF34qzUzKcg","count":1},{"value":"DdcPDlmBgEtZkVifhhgXFw","count":1},{"value":"NxBMZ4lsaztf9QPyfHF15A","count":1},{"value":"cyKozbku4BaJ7eDOJoAZkQ","count":1},{"value":"rzB1DaV7quICiMSyUHNAHg","count":1},{"value":"99R6iZE7Jp_wm-kKuvPghg","count":1},{"value":"h9Rn8tXMDsUL9bBnWVLI2A","count":1},{"value":"jAulhReRyZiRAYWgU9f-cQ","count":1},{"value":"cMzZTHjZhE8mo0lpDSJS5A","count":1},{"value":"l8YHBCKtPw8wLgt-OC3e3w","count":1},{"value":"6V-gUB2h6Qxel407ZyuGQQ","count":1},{"value":"76oVt5FW0zX755NK0moPnw","count":1},{"value":"-sdSYWZ4o5Qp_HHdQniqng","count":1},{"value":"Y7LG75Jq6mGwUzTYxdKKJg","count":1},{"value":"0y2WNztGiW0pUr-e1kDWCg","count":1},{"value":"4HwapqgvhF4kyMjIV8y-Xg","count":1},{"value":"nQtH8ZbwDDzAM1MeqDGxGw","count":1}],"count":43},{"key":"wheelchair","tags":[{"value":"yes","count":14},{"value":"limited","count":11},{"value":"no","count":7}],"count":32},{"key":"note","tags":[{"value":"Voir https://wiki.openstreetmap.org/wiki/WikiProject_CircularEconomy pour conseils de cartographie.","count":12},{"value":"Accrochée à un arbre","count":1},{"value":"accessible aux heures d'ouverture du magasin Biocoop Scarabée","count":1},{"value":"accessible aux heures d'ouverture du Noroît","count":1},{"value":"Voir https://wiki.openstreetmap.org/wiki/WikiProject_CircularEconomy pour conseils de cartographie. ","count":1},{"value":"boîte gérée par un privé et présente seulement en été","count":1},{"value":"Cabane à dons (pas seulement livres)","count":1}],"count":18},{"key":"picture","tags":[{"value":"https://upload.wikimedia.org/wikipedia/commons/5/52/BoiteALivresRueDunantStAvertin.jpg","count":1},{"value":"https://upload.wikimedia.org/wikipedia/commons/e/e3/Bo%C3%AEte_%C3%A0_livres_Saint_Genouph.jpg","count":1},{"value":"https://upload.wikimedia.org/wikipedia/commons/5/5b/Boite_%C3%A0_livres_Savonnieres.jpg","count":1},{"value":"https://upload.wikimedia.org/wikipedia/commons/c/c5/Bo%C3%AEte_%C3%A0_livres_Courteline_Preuilly_Tours.jpg","count":1},{"value":"https://upload.wikimedia.org/wikipedia/commons/7/71/BoiteALivresMorier.jpg","count":1},{"value":"https://upload.wikimedia.org/wikipedia/commons/6/6e/BoiteALivresPerriersChambray.jpg","count":1},{"value":"https://upload.wikimedia.org/wikipedia/commons/3/33/BoiteALivresEcoleMBastieChambray.jpg","count":1},{"value":"https://upload.wikimedia.org/wikipedia/commons/f/fb/BoiteALivresGlorietteTours.jpg","count":1},{"value":"https://upload.wikimedia.org/wikipedia/commons/c/c1/BoiteALivresPapoterieChambray.jpg","count":1},{"value":"https://upload.wikimedia.org/wikipedia/commons/3/3c/BoiteALivresMontjoyeuxTours.jpg","count":1},{"value":"https://upload.wikimedia.org/wikipedia/commons/6/62/Bo%C3%AEte_%C3%A0_livres_Berthenay.jpg","count":1},{"value":"https://upload.wikimedia.org/wikipedia/commons/6/67/Boite_%C3%A0_livres_Montbazon.jpg","count":1},{"value":"https://upload.wikimedia.org/wikipedia/commons/d/d5/Bo%C3%AEte_%C3%A0_livres_place_de_Strasbourg_Tours.jpg","count":1},{"value":"https://upload.wikimedia.org/wikipedia/commons/c/cc/Bo%C3%AEte_%C3%A0_livres_Pr%C3%A9bendes_Tours.jpg","count":1},{"value":"https://upload.wikimedia.org/wikipedia/commons/d/da/Bo%C3%AEte_%C3%A0_livres_Champ_joli_Tours.jpg","count":1}],"count":15},{"key":"location","tags":[{"value":"indoor","count":7},{"value":"outdoor","count":6}],"count":13},{"key":"charity","tags":[{"value":"yes","count":11}],"count":11},{"key":"wikimedia_commons","tags":[{"value":"File:Public_bookcase_-_Chambéry_.jpg","count":1},{"value":"File:Offener_Buecherschrank_Basel-St._Johann_1.jpg","count":1},{"value":"File:Boîte à livres au Parc Brosset, Rillieux-la-Pape (2).jpg","count":1},{"value":"File:Boîte à livres, Place Bruno Polga (Saint-Priest).jpg","count":1},{"value":"File:Belleville (Rhône) - Boîte à livres (août 2018).jpg","count":1},{"value":"File:Boîte à livres, parking Crépieux, Caluire-et-Cuire, juillet 2019 (2).jpg","count":1},{"value":"File:Bibliothèque participative du Carrefour de Saint-Égrève.jpg","count":1},{"value":"File:Microbibliothèque à la salle des fêtes de Tramoyes.jpg","count":1},{"value":"File:Microbibliothèque sur un mur extérieur de l'école de Tramoyes.jpg","count":1}],"count":9},{"key":"recycling:books","tags":[{"value":"yes","count":9}],"count":9},{"key":"material","tags":[{"value":"wood","count":8},{"value":"cardboard","count":1}],"count":9},{"key":"image","tags":[{"value":"https://upload.wikimedia.org/wikipedia/commons/thumb/1/1d/Public_bookcase_-_Chamb%C3%A9ry_.jpg/320px-Public_bookcase_-_Chamb%C3%A9ry_.jpg","count":1},{"value":"https://commons.wikimedia.org/wiki/File:Bo%C3%AEte_%C3%A0_livres_au_hameau_des_%C3%89chets_%C3%A0_Miribel_(Ain).JPG","count":1},{"value":"https://commons.wikimedia.org/wiki/File:Buffard_(Doubs)_le_5_janvier_2018_-_3.jpg","count":1},{"value":"https://commons.wikimedia.org/wiki/File:Bo%C3%AEte_%C3%A0_livres_de_Soug%C3%A8res-en-Puisaye,_Yonne,_France_-_2.JPG","count":1},{"value":"https://commons.wikimedia.org/wiki/File:Beynost_(Ain,_France)_-_oct_2017_-_bo%C3%AEte_%C3%A0_livres.JPG","count":1},{"value":"https://commons.wikimedia.org/wiki/File:Bo%C3%AEte_%C3%A0_livres_%C3%A0_Miribel_(Ain)_-_quartier_Saint-Martin_-_1.JPG","count":1},{"value":"File:Aspères-Espace multimédia-20190327.jpg","count":1},{"value":"https://photos.app.goo.gl/wPm3WQnE9Lnyznja7","count":1}],"count":8},{"key":"survey:date","tags":[{"value":"2018-11-24","count":1},{"value":"2018-02-11","count":1},{"value":"2016-11-02","count":1},{"value":"2016-11-27","count":1},{"value":"2018-11-04","count":1},{"value":"2018-02-10","count":1},{"value":"2018-10-25","count":1}],"count":7},{"key":"covered","tags":[{"value":"yes","count":6}],"count":6},{"key":"access","tags":[{"value":"yes","count":5},{"value":"customers","count":1}],"count":6},{"key":"recycling_type","tags":[{"value":"container","count":5}],"count":5},{"key":"level","tags":[{"value":"0","count":5}],"count":5},{"key":"fee","tags":[{"value":"no","count":5}],"count":5},{"key":"disused:amenity","tags":[{"value":"telephone","count":4}],"count":4},{"key":"brand","tags":[{"value":"Livres Voyageurs","count":1},{"value":"Lions-France","count":1},{"value":"Bois La Combe","count":1},{"value":"Vival Livres","count":1}],"count":4},{"key":"wikidata","tags":[{"value":"Q47164584","count":1},{"value":"Q51264150","count":1},{"value":"Q53733828","count":1},{"value":"Q55333255","count":1}],"count":4},{"key":"operator:type","tags":[{"value":"government","count":4}],"count":4},{"key":"email","tags":[{"value":"bibliothecaires@mairie-nanterre.fr","count":1},{"value":"conseilsdequartier@ville-issy.fr","count":1},{"value":"cabanealivres@mairie-toul.fr","count":1}],"count":3},{"key":"start_date","tags":[{"value":"2017","count":1},{"value":"2018-03-24","count":1},{"value":"2017-10-18","count":1}],"count":3},{"key":"public_transport","tags":[{"value":"stop_position","count":3}],"count":3},{"key":"phone","tags":[{"value":"+33147295157","count":1},{"value":"+33 4 92 31 28 49","count":1},{"value":"+33 5 45 82 88 01","count":1}],"count":3},{"key":"bus","tags":[{"value":"yes","count":3}],"count":3},{"key":"note:fr","tags":[{"value":"Depuis le 23 mai 2018","count":2}],"count":2},{"key":"bench","tags":[{"value":"yes","count":2}],"count":2},{"key":"tourism","tags":[{"value":"attraction","count":1},{"value":"artwork","count":1}],"count":2},{"key":"support","tags":[{"value":"mural","count":1},{"value":"tree","count":1}],"count":2},{"key":"fixme","tags":[{"value":"Position à affiner","count":1},{"value":"position","count":1}],"count":2},{"key":"was:amenity","tags":[{"value":"telephone","count":1}],"count":1},{"key":"inscription","tags":[{"value":"dons échange lecture partage","count":1}],"count":1},{"key":"artwork_type","tags":[{"value":"sculpture","count":1}],"count":1},{"key":"fax","tags":[{"value":"+33141370647","count":1}],"count":1},{"key":"internet_access","tags":[{"value":"yes","count":1}],"count":1},{"key":"internet_access:fee","tags":[{"value":"no","count":1}],"count":1},{"key":"type","tags":[{"value":"reading_box","count":1}],"count":1},{"key":"website:catalogue","tags":[{"value":"https://www.nanterre.fr/1052-le-catalogue.htm","count":1}],"count":1},{"key":"disused:ref","tags":[{"value":"1007","count":1}],"count":1},{"key":"booth","tags":[{"value":"yes","count":1}],"count":1},{"key":"shop","tags":[{"value":"books","count":1}],"count":1},{"key":"second_hand","tags":[{"value":"only","count":1}],"count":1},{"key":"artist:wikidata","tags":[{"value":"Céline Dro","count":1}],"count":1},{"key":"indoor","tags":[{"value":"yes","count":1}],"count":1}]