[{"key":"amenity","tags":[{"value":"public_bath","count":26}],"count":26},{"key":"bath:type","tags":[{"value":"thermal","count":11},{"value":"hammam","count":8},{"value":"float_spa","count":1},{"value":"hot_spring","count":1}],"count":21},{"key":"operator","tags":[{"value":"Chaîne Thermale du Soleil","count":1},{"value":"Thermes de Capvern Les Bains","count":1},{"value":"Les Thermes d'Argeles-Gazost","count":1},{"value":"Les Thermes de Barèges/Barzun","count":1},{"value":"Les Thermes de Luz-Saint-Sauveur","count":1},{"value":"SARL AMAN-IMAN","count":1},{"value":"Valvital","count":1}],"count":7},{"key":"website","tags":[{"value":"https://www.experience-silence.com/","count":1},{"value":"http://www.hammam-du-canal.com","count":1},{"value":"https://www.valvital.fr/stations-thermales/lons-le-saunier/accueil-lons-le-saunier.html","count":1},{"value":"https://www.chainethermale.fr/le-boulou.html","count":1},{"value":"http://www.dampfbadbasel.ch/","count":1},{"value":"https://www.nomad-et-sens.com","count":1},{"value":"http://www.bulledeplaisir.com/","count":1}],"count":7},{"key":"fee","tags":[{"value":"yes","count":6},{"value":"no","count":1}],"count":7},{"key":"beauty","tags":[{"value":"yes","count":4}],"count":4},{"key":"hammam","tags":[{"value":"yes","count":4}],"count":4},{"key":"leisure","tags":[{"value":"sauna","count":2},{"value":"swimming_area","count":1}],"count":3},{"key":"bath:open_air","tags":[{"value":"no","count":2},{"value":"yes","count":1}],"count":3},{"key":"fitness_centre","tags":[{"value":"yes","count":2},{"value":"no","count":1}],"count":3},{"key":"massage","tags":[{"value":"yes","count":3}],"count":3},{"key":"phone","tags":[{"value":"+33 1 42 49 75 73","count":1},{"value":"+33 3 84 24 20 34","count":1}],"count":2},{"key":"sauna","tags":[{"value":"yes","count":2}],"count":2},{"key":"note","tags":[{"value":"Caissons de flottaison","count":1}],"count":1},{"key":"bath:sand_bath","tags":[{"value":"no","count":1}],"count":1},{"key":"spa","tags":[{"value":"therme","count":1}],"count":1},{"key":"tourism","tags":[{"value":"spa_resort","count":1}],"count":1},{"key":"description","tags":[{"value":"Probably a thermal spa not a water park.","count":1}],"count":1},{"key":"level","tags":[{"value":"0","count":1}],"count":1},{"key":"brand","tags":[{"value":"Valvital","count":1}],"count":1},{"key":"brand:wikidata","tags":[{"value":"Q16682285","count":1}],"count":1},{"key":"ref:FR:FINESS","tags":[{"value":"320003734","count":1}],"count":1},{"key":"access","tags":[{"value":"yes","count":1}],"count":1},{"key":"sport","tags":[{"value":"swimming","count":1}],"count":1},{"key":"wheelchair","tags":[{"value":"yes","count":1}],"count":1}]