[{"key":"shop","tags":[{"value":"locksmith","count":165}],"count":165},{"key":"phone","tags":[{"value":"+41 61 481 20 20","count":1},{"value":"+334 67 605 655","count":1},{"value":"+33 2 30 96 41 23","count":1},{"value":"+33 1 42 81 04 24","count":1},{"value":"+33 4 78 27 33 75","count":1},{"value":"+33 1 43 21 40 14","count":1},{"value":"+33 2 47 38 68 51","count":1},{"value":"+33 3 86 61 33 83","count":1},{"value":"+33 1 42 28 99 44","count":1},{"value":"+33 2 97 40 78 03","count":1},{"value":"+33 1 47 39 62 24","count":1},{"value":"+33 1 55 90 28 70","count":1},{"value":"+33 1 41 05 42 40;+33 1 47 41 05 42 45","count":1},{"value":"+33 1 46 04 39 06","count":1},{"value":"+33 478 84 24 71","count":1},{"value":"+33 1 42 55 43 68","count":1},{"value":"+33 6 76 77 82 86","count":1},{"value":"+33 2 40 59 66 29","count":1},{"value":"+33232080802","count":1},{"value":"+33 4 78 89 32 05","count":1},{"value":"+33 5 61 32 00 00","count":1},{"value":"+33 2 99 78 24 96","count":1},{"value":"+33 3 88 75 50 20","count":1},{"value":"+33 3 82 83 31 79","count":1},{"value":"+33 1 47 40 11 26","count":1},{"value":"+33 3 85 53 11 21","count":1}],"count":26},{"key":"website","tags":[{"value":"https://misterminit.eu/","count":1},{"value":"https://www.serruriers-montpellier.fr/","count":1},{"value":"http://www.fichet-pointfort.fr/","count":1},{"value":"http://www.serrurerie-cabannes.com","count":1},{"value":"https://www.bvm-fermetures-serrure-rapid.fr/","count":1},{"value":"http://www.amiens-serrurerie-fermetures-protection.fr/","count":1},{"value":"https://bezian.fr/","count":1},{"value":"https://www.serrurerie-17paris.fr/","count":1},{"value":"http://www.alloserrure.com","count":1},{"value":"https://ats-sicherheitstechnik.ch/","count":1},{"value":"http://osv-serrurier-vitrier-lyon.com/serrurerie/serrurier-lyon-2eme-arrondissement/","count":1},{"value":"https://www.blondeau-serrurerie-ferney.fr/","count":1},{"value":"http://www.abhabitat.fr/","count":1},{"value":"https://www.facebook.com/cssportes/","count":1},{"value":"https://www.serrurerie-martin.com/","count":1},{"value":"http://www.serrurerie-serrurier-arlon-luxembourg.be","count":1},{"value":"https://www.balmarspu.com","count":1}],"count":17},{"key":"craft","tags":[{"value":"shoemaker","count":8},{"value":"locksmith","count":3},{"value":"key_cutter","count":3},{"value":"plumber;glaziery;hvac","count":1},{"value":"plumber","count":1}],"count":16},{"key":"operator","tags":[{"value":"Minit","count":1},{"value":"Baroukh Stéphane","count":1},{"value":"Minit France","count":1},{"value":"Alain Tüscher","count":1},{"value":"OSV Serrurier Vitrier Lyon","count":1},{"value":"M. Thierry Julien et M. Bertrand Colomb","count":1},{"value":"EURL T.L.C Michel MARTIN","count":1},{"value":"Christian Bouillet","count":1}],"count":8},{"key":"wheelchair","tags":[{"value":"yes","count":3},{"value":"no","count":3},{"value":"limited","count":1}],"count":7},{"key":"level","tags":[{"value":"0","count":5}],"count":5},{"key":"email","tags":[{"value":"contact@centresecurite.fr","count":1},{"value":"info@protectionplus.eu","count":1},{"value":"serrurerie.blondeau@orange.fr","count":1},{"value":"christian-bouillet@orange.fr","count":1}],"count":4},{"key":"description","tags":[{"value":"Serrurerie générale, dépannage et ouverture de porte, reproduction de clés, installation d'alarmes.","count":1},{"value":"Portes Blindée - Serrure","count":1},{"value":"Multi-services : point relais, clés minute, gravure, faire-parts, carte de visite, tampons, plaques pro","count":1},{"value":"serrurerie, coffre fort, portes blindées","count":1}],"count":4},{"key":"survey:date","tags":[{"value":"2017-07-21","count":1},{"value":"2017-07-16","count":1},{"value":"2017-09-05","count":1}],"count":3},{"key":"brand","tags":[{"value":"Allianz Services","count":1},{"value":"Point Fort Fichet","count":1}],"count":2},{"key":"fax","tags":[{"value":"+33 2 99 79 40 48","count":1},{"value":"+33 85 53 09 42","count":1}],"count":2},{"key":"payment:cash","tags":[{"value":"yes","count":2}],"count":2},{"key":"brand:wikipedia","tags":[{"value":"fr:Mister Minit","count":1}],"count":1},{"key":"created_by","tags":[{"value":"iLOE 1.9","count":1}],"count":1},{"key":"payment:visa","tags":[{"value":"yes","count":1}],"count":1},{"key":"payment:credit_cards","tags":[{"value":"yes","count":1}],"count":1},{"key":"payment:mastercard","tags":[{"value":"yes","count":1}],"count":1},{"key":"note","tags":[{"value":"Ferronnerie, Serrurerie","count":1}],"count":1},{"key":"wheelchair:step_height","tags":[{"value":"9","count":1}],"count":1},{"key":"payment:cheque","tags":[{"value":"yes","count":1}],"count":1},{"key":"ref:FR:NAF","tags":[{"value":"4674B","count":1}],"count":1},{"key":"ref:FR:SIRET","tags":[{"value":"31659833300037","count":1}],"count":1},{"key":"office","tags":[{"value":"company","count":1}],"count":1},{"key":"mapillary","tags":[{"value":"bNVxSzfyam9YI5zZuyRg4A","count":1}],"count":1},{"key":"entrance","tags":[{"value":"yes","count":1}],"count":1}]