[{"key":"shop","tags":[{"value":"yes","count":3092}],"count":3092},{"key":"website","tags":[{"value":"https://misterminit.eu/","count":4},{"value":"https://www.comptoir-irlandais.com/","count":3},{"value":"http://espace-sfr.sfr.fr/espace-sfr/recherche","count":2},{"value":"boutique-jourdefete.com/magasin-thionville","count":1},{"value":"http://www.huilerie-batard.com/","count":1},{"value":"http://yves-rocher.fr/thuir","count":1},{"value":"http://bailleul.cuisines-schmidt.com/","count":1},{"value":"http://www.vieux-chateau.com","count":1},{"value":"www.tcra.fr","count":1},{"value":"https://www.ligneverte.fr/","count":1},{"value":"www.accumot-ets-didier.com","count":1},{"value":"https://www.anne-de-solene.com/","count":1},{"value":"https://www.cash-fetes.fr//","count":1},{"value":"http://www.pieces-montees.fr/","count":1},{"value":"http://www.naturhouse.com/","count":1},{"value":"https://streetshop-france.fr/","count":1},{"value":"http://www.photo-express.fr","count":1},{"value":"http://parquet2d.free.fr/","count":1},{"value":"http://www.elfenature.com/","count":1},{"value":"http://www.hygena.fr/","count":1},{"value":"http://pcokaz.fr/","count":1},{"value":"www.lemondedemelusine.fr","count":1},{"value":"www.verandasrogerautaa.com","count":1},{"value":"https://www.atout-peinture.fr/","count":1},{"value":"http://comptoir-irlandais.com","count":1},{"value":"http://www.sante-globale.fr/","count":1},{"value":"https://www.bca-materiauxanciens.com/","count":1},{"value":"www.rheso.fr","count":1},{"value":"http://alpha-loisirs.fr/","count":1},{"value":"https://www.manzoni-freres.fr/","count":1},{"value":"https://www.laboutiqueduchampignon.com/","count":1},{"value":"http://www.etiketbioty.fr","count":1},{"value":"https://agence.orange.fr/5999-boutique-orange-antibes","count":1},{"value":"http://www.wuerth-ag.ch","count":1},{"value":"https://www.cldesign45.fr/","count":1},{"value":"http://www.kesoa.com/notre-epicerie-fine","count":1},{"value":"http://mademoiselleetvous.com/site/","count":1},{"value":"http://www.medor-et-moi.com","count":1},{"value":"https://www.options.fr/","count":1},{"value":"http://bazarsaintjoseph.fr","count":1},{"value":"https://atelierdeschimeres.fr/","count":1},{"value":"http://www.murano.nu","count":1},{"value":"http://magasin.comptoir-de-famille.com/31265-comptoir-de-famille-orleans","count":1},{"value":"http://www.oliviers-co.com","count":1},{"value":"https://www.fleursdedragees.com/","count":1},{"value":"http://www.cppo-orleans.com","count":1},{"value":"http://www.espaces-loisirs.com","count":1},{"value":"http://www.azap.fr","count":1},{"value":"https://www.artispose.fr/","count":1},{"value":"http://www.arrow-airsoft.com","count":1},{"value":"https://www.dubruitdanslacuisine.fr/","count":1},{"value":"http://www.gilbertmethivier.fr/","count":1},{"value":"http://www.e-leclerc.com/espace+culturel","count":1},{"value":"http://coudert.tv","count":1},{"value":"https://www.tereva.fr/","count":1},{"value":"http://www.savonduchaudron.com/","count":1},{"value":"http://www.fusions-creations.com/","count":1},{"value":"http://www.jouvenaud.com/","count":1},{"value":"http://www.terre-verre.fr","count":1},{"value":"https://www.jeuxbois-toc.com/","count":1},{"value":"http://www.sophiepinard.com/","count":1},{"value":"http://www.atelierducuir-lagacilly.fr/","count":1},{"value":"http://www.bougiesbougeoirs.fr/","count":1},{"value":"http://www.taxi-guillemin.fr","count":1},{"value":"https://www.bretagnecarburation.fr/","count":1},{"value":"https://www.conceptstore3d.com/","count":1},{"value":"https://www.elec45.com/","count":1},{"value":"https://www.mbe-franchising.fr","count":1},{"value":"http://www.schoendistribution.com/","count":1},{"value":"https://www.wearepirouette.fr/","count":1},{"value":"http://www.ideesbois.net/magasin-bois/","count":1},{"value":"http://www.est-pluie.fr/","count":1},{"value":"https://www.centrakor.com/magasin-centrakor/millaffai1/mill-rsquo-affaires-amilly-45200.html/","count":1},{"value":"https://www.bonial.fr/Magasins/Amilly/Casa-rue-de-L-europe/v-f248434158","count":1},{"value":"http://www.boutique-jourdefete.com/magasin-jour-de-fete-montargis","count":1},{"value":"http://www.maxizoo.fr/magasin/montargis.html","count":1},{"value":"https://www.ambianceetstyles.com/magasins/voir/10090","count":1},{"value":"http://www.formeetzen.fr/","count":1},{"value":"https://www.comptoirdeceram.com/","count":1},{"value":"https://www.fnac.com/","count":1},{"value":"https://www.artisansdumonde.org/les-associations-locales/artisans-du-monde-valence","count":1},{"value":"http://www.debeaux-chauffage-26.fr/","count":1},{"value":"http://grandsespaces-parapente-annecy.com/","count":1},{"value":"http://www.grout33.com/","count":1},{"value":"http://www.cultura.com","count":1},{"value":"https://www.canoe-tarn.com/","count":1},{"value":"http://yogat.free.fr/","count":1},{"value":"http://www.moventeam.fr/","count":1},{"value":"https://depotventekerhau.wixsite.com/kerhau","count":1},{"value":"https://www.oxfamfrance.org/","count":1},{"value":"https://www.bureau-vallee.fr/","count":1},{"value":"https://www.magasin-point-vert.fr/magasin/pleyben","count":1},{"value":"https://www.location-skis-labresse.fr/fr","count":1},{"value":"http://www.smpierrel.fr/","count":1},{"value":"http://minoteriegouzene.com","count":1},{"value":"http://www.tikita.fr","count":1},{"value":"https://www.christaud.com/","count":1},{"value":"www.coutellerie-faget.com","count":1},{"value":"https://enventelibre.org/fr/","count":1},{"value":"http://www.styl-habitat.fr/agence/constructeur-nevers","count":1},{"value":"https://www.easycash.fr/","count":1},{"value":"http://www.hetatelier.be/","count":1},{"value":"https://azae.net/","count":1},{"value":"http://www.monboudoirbobo.com","count":1},{"value":"http://www.citedia.fr","count":1},{"value":"http://www.neptunia.com/","count":1},{"value":"https://www.facebook.com/commerceboutdumonde/","count":1},{"value":"https://www.labaux.org","count":1},{"value":"https://www.parkerfrance.fr/services/parkerstore.html","count":1},{"value":"https://www.facebook.com/nevers.peche/","count":1},{"value":"http://osmosource.fr/","count":1},{"value":"https://fr.agenceauto.com/fr/agence-cannes-alpes-maritimes-8.html","count":1},{"value":"https://www.ludospace.com/","count":1},{"value":"http://www.petswouaftitud.fr/","count":1},{"value":"https://www.domainedecoucouzac.fr/","count":1},{"value":"https://www.carrelage-dela-tuilerie.com/","count":1},{"value":"http://www.lamaisonpernoise.com/","count":1},{"value":"http://www.e-leclerc.com/guingamp","count":1},{"value":"https://www.laboiteapiles.com/","count":1},{"value":"http://www.rennesbatteries.com/","count":1},{"value":"http://www.forumplus.fr/fr/flers---la-lande-patry--61--gc17.html","count":1},{"value":"https://www.panafrica-store.com/","count":1},{"value":"https://aujourdhui-demain.com/","count":1},{"value":"https://www.marius-fabre.com/fr/content/41-boutique-savon-de-marseille-paris","count":1},{"value":"http://www.cordonnerie-cles-remiremont.fr/","count":1},{"value":"https://www.rougegorge.com/nos-magasins/magasin-remiremont-6329","count":1},{"value":"http://www.dlice.fr/boutiques-eliquide/remiremont/319149-clope-store#","count":1},{"value":"http://www.ethics.fr","count":1},{"value":"http://www.bebeclindoeil.fr/","count":1},{"value":"https://www.untempspourvous.fr/femme-de-menage/14-agence-montrouge","count":1},{"value":"https://www.mbefrance.fr/fr","count":1},{"value":"http://www.dietplus.fr","count":1},{"value":"https://www.cookme-shop.com/","count":1},{"value":"http://www.anti-cafard2000.com/","count":1},{"value":"https://www.mauduitsports.com/","count":1},{"value":"https://www.glc-creations.com/","count":1},{"value":"http://www.makadamshop.fr/","count":1},{"value":"https://www.naturhouse.fr/liste-centres/221-remiremont/","count":1},{"value":"http://www.at2e.fr","count":1},{"value":"http://www.als-motoculture.fr/","count":1},{"value":"https://www.alpha-service-ouest.com/","count":1},{"value":"http://www.monsieurmeublealencon.com/","count":1},{"value":"https://www.bleulibellule.com/magasins/bleu-libellule-alencon.html","count":1},{"value":"https://www.tibledumontetfils.com/","count":1},{"value":"http://www.pierres-decor.net/","count":1},{"value":"https://www.glastint.com/centres/montrouge/","count":1},{"value":"http://www.boutiquedelaviedurail.com","count":1},{"value":"http://www.maxplus.fr/magasin-45-mulsanne.php","count":1},{"value":"http://www.mpofenetres.com/agence/agence-du-mans-26.xhtml","count":1},{"value":"https://www.rougier-ple.fr/magasin/rougier-ple-le-mans.r.html","count":1},{"value":"stellaboutique.net","count":1},{"value":"https://www.naturhouse.fr/trouver-un-centre/?idcentre=264","count":1},{"value":"http://www.revedebleu.com/","count":1},{"value":"earldupfaffenbach.fr","count":1},{"value":"https://www.apartix.ch/","count":1},{"value":"http://shanghai-style-shop.fr/","count":1},{"value":"http://www.callyope.com/","count":1},{"value":"http://www.domhomtic.com","count":1},{"value":"https://www.sensomedia.com","count":1},{"value":"https://www.adour-securite.fr/","count":1},{"value":"https://www.ab-navigation.com/","count":1},{"value":"https://fonderieobertino.jimdo.com/","count":1},{"value":"http://www.thekase.com","count":1},{"value":"http://3dadvance.fr/","count":1},{"value":"https://www.orencash.fr/boutiques-achat-or/tarare/","count":1},{"value":"http://www.la-coupe-aux-as.com","count":1},{"value":"http://galerie-saluden.com/","count":1},{"value":"http://www.smac-sa.com/","count":1},{"value":"https://www.tryba.com/","count":1},{"value":"http://www.lodge-boutique.fr/","count":1},{"value":"https://www.heytens.fr","count":1},{"value":"http://www.batteries76.com/","count":1},{"value":"http://www.relay.fr","count":1},{"value":"https://www.sundance-spas.fr/distributeurs/sundance-spas-dijon-59.htm","count":1},{"value":"http://www.grandsire-chauffage.fr/","count":1},{"value":"http://www.ohmled.fr/","count":1},{"value":"https://fr-fr.facebook.com/pages/category/Local-Business/Univers-Carte-Grise-661938220670894/","count":1},{"value":"https://www.ultrasons-nevers.fr/","count":1},{"value":"https://www.welkit.fr/","count":1},{"value":"http://www.arts-fx.com","count":1},{"value":"http://veganosh.wordpress.com","count":1},{"value":"http://www.chapin-materiel.com/","count":1},{"value":"https://www.jfm.fr/","count":1},{"value":"sti-cazet.com","count":1},{"value":"https://www.milongamusic.com/","count":1},{"value":"https://www.ladroguerie.com/","count":1},{"value":"https://www.stmichel.fr/","count":1},{"value":"http://www.lareservedesarts.org/","count":1},{"value":"https://www.maxplus.fr/magasin-51-ramonville.php","count":1},{"value":"https://www.tondoland.com/","count":1},{"value":"http://www.amdmedical.fr/","count":1},{"value":"https://agence.loxam.fr/899-loxam-creil-7462","count":1},{"value":"https://www.mabeo-industries.com/","count":1},{"value":"https://www.abris-olivier.com/","count":1},{"value":"http://graphiarts.com","count":1},{"value":"http://www.leszigotaix.fr/","count":1},{"value":"http://www.moulinolivette.fr/","count":1},{"value":"https://www.maison-etanche.com/","count":1},{"value":"http://www.auptitboulon-motoculture.com/","count":1},{"value":"https://www.centrakor.com/magasin-centrakor/millaffai1/centrakor-amilly-45200.html","count":1},{"value":"https://barbecue-co.com/","count":1},{"value":"zoeconfetti.fr","count":1},{"value":"https://www.wm88.fr/","count":1},{"value":"http://www.constructeurdepiscines.com/","count":1},{"value":"https://www.culligan.fr/reseau-culligan/sud-lorraine","count":1},{"value":"https://www.bleulibellule.com/","count":1},{"value":"https://www.pointmariage.com/fr","count":1},{"value":"https://www.padd.fr/nos-magasins/43-nancy","count":1},{"value":"https://www.cedeo.fr/","count":1},{"value":"https://www.cera-mod.fr/","count":1},{"value":"https://www.integralpeche.fr/","count":1},{"value":"https://www.vie-veranda.com/creation-veranda","count":1},{"value":"https://www.stokomani.fr/","count":1},{"value":"https://www.jardincomtois.com/","count":1},{"value":"https://www.macarondesaintecroix.com/","count":1},{"value":"https://www.go2sante.com/","count":1},{"value":"https://www.bureau-vallee.fr/nos-magasins/magasin-ploeren-vannes-14/","count":1},{"value":"http://www.biogolfe.org","count":1},{"value":"https://www.centrakor.com/","count":1},{"value":"https://www.platten-fliesen-kurt-koch.de/","count":1},{"value":"https://m.spar.fr/centre-magasin-spar-cher-18/commerce-culan-groupe-casino/magasin-tl510.html","count":1},{"value":"http://www.nsa-sonorisation.com/","count":1},{"value":"www.reines-de-touraine.com","count":1},{"value":"controle-technique.autosur.com","count":1},{"value":"https://www.conforama.fr/magasins-conforama/MONTARGIS?lat=0&long=0&name=MONTARGIS","count":1},{"value":"https://www.everblue.com/concessionnaires/everblue-saint-jean-du-falga/","count":1},{"value":"http://www.avecstyles.fr","count":1},{"value":"https://www.troc.com/","count":1},{"value":"http://www.espaceterrena.fr/","count":1},{"value":"https://www.confituresduclimont.com/","count":1},{"value":"http://www.cetram.fr/","count":1},{"value":"https://www.kei-stone.fr/","count":1},{"value":"http://sellerie-clos-rimbaud-boutique.com","count":1},{"value":"https://magasins.easycash.fr/","count":1},{"value":"https://www.breuilhorticulture.fr","count":1},{"value":"http://espacerevetements-lorient.fr/","count":1},{"value":"http://www.enseignes-charpentier.fr","count":1},{"value":"https://reims.mondial-piscine.eu/","count":1},{"value":"http://www.srkfenetre.fr/index.php","count":1},{"value":"https://www.stardec.fr/","count":1},{"value":"http://www.compagnons-peintres.fr/","count":1},{"value":"https://www.champagnesonorisation.fr/","count":1},{"value":"https://www.groupecham.com/agences/reims/","count":1}],"count":249},{"key":"phone","tags":[{"value":"+33 3 88 68 93 57","count":2},{"value":"+33320129247","count":2},{"value":"+33 4 91 77 62 56","count":1},{"value":"+33 1 80 50 28 09","count":1},{"value":"+33 5 49 51 20 16","count":1},{"value":"+33 3 29 63 42 42","count":1},{"value":"+33 3 29 63 47 33","count":1},{"value":"+33 3 29 60 88 34","count":1},{"value":"+33 5 55 72 48 74","count":1},{"value":"+33328485799","count":1},{"value":"+33328405353","count":1},{"value":"+33 2 35 21 16 25","count":1},{"value":"+33 2 96 14 62 32","count":1},{"value":"+33237210745","count":1},{"value":"+33 4 32 74 18 32","count":1},{"value":"+33467401560","count":1},{"value":"+33 3 29 60 04 56","count":1},{"value":"+33 3 29 60 49 17","count":1},{"value":"+33 3 29 60 90 42","count":1},{"value":"+33 3 29 63 63 57","count":1},{"value":"+33 3 29 56 86 15","count":1},{"value":"+33 6 58 68 01 25","count":1},{"value":"+33 9 83 51 23 41","count":1},{"value":"+33468392470","count":1},{"value":"+33 4 68 78 12 62","count":1},{"value":"+33 3 29 41 22 50","count":1},{"value":"+33556910178","count":1},{"value":"+332 31 85 74 00","count":1},{"value":"+33 1 64 61 12 20","count":1},{"value":"+33 3 28 50 28 97","count":1},{"value":"+33972542818","count":1},{"value":"+33 2 41 61 62 40","count":1},{"value":"+33 1 42042605","count":1},{"value":"+33 3 81 63 78 82","count":1},{"value":"+33 3 89232607","count":1},{"value":"+41 61 481 18 03","count":1},{"value":"+33 6 20 59 30 91","count":1},{"value":"+33 1 30 26 02 73","count":1},{"value":"+33 2 40 96 81 15","count":1},{"value":"+33 2 53 87 90 99","count":1},{"value":"+33 2 40 83 07 19","count":1},{"value":"+33 1 46 85 09 34","count":1},{"value":"+33 1 41 61 95 86","count":1},{"value":"+33 4 93 80 50 50","count":1},{"value":"+33561040020","count":1},{"value":"+33 534140317","count":1},{"value":"+33 3 44 03 14 16","count":1},{"value":"+33 2 99 08 22 75","count":1},{"value":"+33 6 84 19 68 41","count":1},{"value":"+33 2 99 08 55 13","count":1},{"value":"+33 6 08 86 18 62","count":1},{"value":"+33 2 99 08 26 68","count":1},{"value":"+33 6 46 10 21 78","count":1},{"value":"+33 2 99 08 11 58","count":1},{"value":"+33 6 79 14 02 93","count":1},{"value":"+33 2 99 08 19 78","count":1},{"value":"+33 2 99 08 23 14","count":1},{"value":"+33 2 99 93 21 68","count":1},{"value":"+33437021418","count":1},{"value":"+33474852612","count":1},{"value":"+33 4 67 57 97 09","count":1},{"value":"+33 3 87 36 28 68","count":1},{"value":"+33 2 51 81 56 61","count":1},{"value":"+33 3 29 63 41 41","count":1},{"value":"+33 3 86 57 48 04","count":1},{"value":"+33 9 72 43 32 94","count":1},{"value":"+33 8 99 03 61 28","count":1},{"value":"+33 3 29 24 28 44","count":1},{"value":"+33 6 77 39 55 56","count":1},{"value":"+33 6 60 49 44 23","count":1},{"value":"+33 3 81834456","count":1},{"value":"+33 2 97 40 78 03","count":1},{"value":"+33 4 75 56 34 27","count":1},{"value":"+33 4 75 59 74 35","count":1},{"value":"+33 4 50 60 79 06","count":1},{"value":"+33 2 43 91 45 40","count":1},{"value":"+33 3 29 37 26 76","count":1},{"value":"+33466485760","count":1},{"value":"+33 2 43 92 75 16","count":1},{"value":"+33 2 43 95 01 01","count":1},{"value":"+33 3 29 25 79 16","count":1},{"value":"+33 3 29 25 49 34","count":1},{"value":"+33 5 62 65 32 03","count":1},{"value":"+33 6 36 36 20 00","count":1},{"value":"+33 2 98 56 35 20","count":1},{"value":"+33 4 73 61 01 09","count":1},{"value":"+33 4 78202198","count":1},{"value":"+33 2 35 98 07 00","count":1},{"value":"+33442882803","count":1},{"value":"+33148125555","count":1},{"value":"+33 3 86 36 57 55","count":1},{"value":"+33 3 66 72 80 22","count":1},{"value":"+33 5 56 17 44 61","count":1},{"value":"+33 2 99 65 01 11","count":1},{"value":"+33 2 35 67 14 44","count":1},{"value":"+33 6 42 66 30 66","count":1},{"value":"+33 3 86 71 69 50","count":1},{"value":"+33 3 86 57 02 54","count":1},{"value":"+33 4 93 46 53 24","count":1},{"value":"+33 3 87 55 07 14","count":1},{"value":"+33 3 87 66 24 63","count":1},{"value":"+33 2 51 10 82 32","count":1},{"value":"+33 4 50 58 10 41","count":1},{"value":"+33380224719","count":1},{"value":"+33 2 43 95 47 51","count":1},{"value":"+33 3 54 27 45 45","count":1},{"value":"+33 3 87 83 30 47","count":1},{"value":"+33 2 43 92 41 18","count":1},{"value":"+33 2 43 62 17 50","count":1},{"value":"+33 2 43 92 72 45","count":1},{"value":"+33 2 99 31 78 17","count":1},{"value":"+33 2 96 40 19 40","count":1},{"value":"+33 2 96 92 33 97","count":1},{"value":"+33 9 83 49 42 65","count":1},{"value":"+33 7 68 77 24 55","count":1},{"value":"+33 2 33 64 73 40","count":1},{"value":"+33 3 82 52 48 65","count":1},{"value":"+33 9 81 65 20 01","count":1},{"value":"+33 7 55616131","count":1},{"value":"+33 3 29622223","count":1},{"value":"+33 3 29246439","count":1},{"value":"+33 9 81174245","count":1},{"value":"+33559803422","count":1},{"value":"+33 6 18 20 12 30","count":1},{"value":"+335 59 80 25 57","count":1},{"value":"+33 4 72 31 48 18","count":1},{"value":"+33 2 99 69 56 18","count":1},{"value":"+33 3 21 83 12 62","count":1},{"value":"+336 18 79 12 18","count":1},{"value":"+33.1.53.28.06.44","count":1},{"value":"+33 2 35 60 82 04","count":1},{"value":"+33 4 79 08 63 08","count":1},{"value":"+33 1 46 20 16 72","count":1},{"value":"+33 3 29224582","count":1},{"value":"+33 2 36 56 77 99","count":1},{"value":"+33 3 55220782","count":1},{"value":"+33 2 35 73 81 45","count":1},{"value":"+33 3 29287065","count":1},{"value":"+33 9 84 27 41 07","count":1},{"value":"+33 2 43 24 21 49","count":1},{"value":"+33 2 33 27 60 24","count":1},{"value":"+33 2 33 28 43 02","count":1},{"value":"+33 3 29622010","count":1},{"value":"+33 1 60 18 85 90","count":1},{"value":"+33 3 91 89 49 20","count":1},{"value":"+33 1 49 70 12 16","count":1},{"value":"+33 5 53 65 70 68 # + 33 9 51 32 73 04","count":1},{"value":"+33 6 47 37 44 67","count":1},{"value":"+33553583620","count":1},{"value":"+33 3 29 32 39 92","count":1},{"value":"+33 3 83 39 43 54","count":1},{"value":"+33 3 83 22 29 40","count":1},{"value":"+33 2 56 29 56 02","count":1},{"value":"+33 3 39 31 00 40","count":1},{"value":"+33 3 25 88 33 28","count":1},{"value":"+334 50 02 04 07","count":1},{"value":"+33 2 97 33 93 48","count":1},{"value":"+33 2 43 92 07 17","count":1},{"value":"+33 3 81 69 30 72","count":1},{"value":"+33 6 88 29 09 18","count":1},{"value":"+33 2 35 62 35 89","count":1},{"value":"+33 9 84 53 09 23","count":1},{"value":"+33 325 318 838","count":1},{"value":"+33 3 84 51 75 01","count":1},{"value":"+33 4 74 05 60 07","count":1},{"value":"+33139228962","count":1},{"value":"+33 2 35 07 11 00","count":1},{"value":"+33 2 54 08 26 50","count":1},{"value":"+33 4 78770220","count":1},{"value":"+33143024615","count":1},{"value":"33 493675588","count":1},{"value":"+33 5 65 41 47 62","count":1},{"value":"+33 5 65 41 18 73","count":1},{"value":"+33 5 65 37 16 81","count":1},{"value":"+33 3 89 80 42 55","count":1},{"value":"+33 1 79 51 59 44","count":1},{"value":"+33 2 38223333","count":1},{"value":"+33 1 61 35 02 08","count":1},{"value":"+33 1 61 35 07 06","count":1},{"value":"+33 1 39 97 52 98","count":1},{"value":"+33 2 32 08 06 14","count":1},{"value":"+33 1 39 78 07 35","count":1},{"value":"+33 3 81 55 50 60","count":1},{"value":"+33 3 88 64 73 40","count":1},{"value":"+33 9 67 30 55 33","count":1},{"value":"+33 3 86 37 67 70","count":1},{"value":"+33 3 86 61 55 19","count":1},{"value":"+33 1 49 85 69 35","count":1},{"value":"0561036583","count":1},{"value":"+33 4 72 07 94 97","count":1},{"value":"+33 9 82 31 36 14","count":1},{"value":"+33 2 99 84 21 41","count":1},{"value":"+33 2 99 60 25 57","count":1},{"value":"01 82 01 35 42","count":1},{"value":"+33 2 23 40 45 86","count":1},{"value":"+33,5 59 84 63 67","count":1},{"value":"+352 26665342","count":1},{"value":"+33320553680","count":1},{"value":"+33 3 84 24 50 11","count":1},{"value":"+33 3 84 24 52 54","count":1},{"value":"+33 4 92 72 00 99","count":1},{"value":"+33 4 96 18 09 18","count":1},{"value":"+33 2 40 26 88 76","count":1},{"value":"+33 2 28 07 40 44","count":1},{"value":"+33 3 29 06 11 17","count":1},{"value":"+33 9 61 45 85 94","count":1},{"value":"+33 3 83 22 89 18","count":1},{"value":"+33 3 83 17 61 70","count":1},{"value":"+33 4 88 09 02 99","count":1},{"value":"+33 2 40 88 20 00","count":1},{"value":"+33145111818","count":1},{"value":"+33 2 97 62 20 80","count":1},{"value":"+33 2 99 47 05 96","count":1},{"value":"+33 3 29 94 25 22","count":1},{"value":"+33 3 21 75 50 21","count":1},{"value":"+33 2 47 95 47 46","count":1},{"value":"+33 2 54 06 06 00","count":1},{"value":"+332 54 07 12 12","count":1},{"value":"+33 2 54 07 35 77","count":1},{"value":"+33 2 40 01 40 61","count":1},{"value":"+33 3 88 97 72 01","count":1},{"value":"+33 2 9910416","count":1},{"value":"+33 5 56 55 90 27","count":1},{"value":"+33 2 35 37 52 79","count":1},{"value":"+33 6 15 71 10 03","count":1},{"value":"+33 2 97 76 53 92","count":1},{"value":"+33 3 83 40 06 69","count":1},{"value":"+33 254480462","count":1}],"count":230},{"key":"amenity","tags":[{"value":"fuel","count":70},{"value":"restaurant","count":17},{"value":"cafe","count":8},{"value":"bar","count":6},{"value":"fast_food","count":4},{"value":"pub","count":3},{"value":"car_rental","count":3},{"value":"driving_school","count":2},{"value":"bicycle_rental","count":2},{"value":"food_court","count":1},{"value":"doctors","count":1},{"value":"bureau_de_change","count":1},{"value":"pharmacy","count":1},{"value":"health_facility","count":1},{"value":"toilets","count":1},{"value":"internet_cafe","count":1}],"count":122},{"key":"wheelchair","tags":[{"value":"yes","count":56},{"value":"no","count":39},{"value":"limited","count":20},{"value":"bad","count":1}],"count":116},{"key":"description","tags":[{"value":"Magasin de vente de linge de maison","count":3},{"value":"Caoutchoucs et Plastiques Industriels","count":1},{"value":"Services photo et informatique","count":1},{"value":"articles culinaires","count":1},{"value":"Centre de blanchiment dentaire","count":1},{"value":"agence de communication","count":1},{"value":"retouches vêtements","count":1},{"value":"Vente et transport de combustibles ","count":1},{"value":"vente maintenance de manèges","count":1},{"value":"Tabac","count":1},{"value":"Nutrition et Diététique","count":1},{"value":"Librairie Hikma - Artisanat marocain - Habits - Cosmetiques","count":1},{"value":"Tout pour la fume et le graff","count":1},{"value":"fr:les as du placard","count":1},{"value":"Enseignes et signalétiques","count":1},{"value":"Producteur de Légumes BIO et plants BIO","count":1},{"value":"Chasse - Pêche","count":1},{"value":"Rééducation Alimentaire","count":1},{"value":"Fenêtres Fermetures Bardage Portails Stores","count":1},{"value":"fr:vente de peinture, de vernis","count":1},{"value":"fr:ateliers créatifs","count":1},{"value":"achat antiquités","count":1},{"value":"Perruques, Postiches","count":1},{"value":"linge de maison","count":1},{"value":"Toilettage pour chien et chat","count":1},{"value":"studio photo","count":1},{"value":"agence immobiliere","count":1},{"value":"Artisanat du monde","count":1},{"value":"Rééducation alimentaire","count":1},{"value":"Moutarderie","count":1},{"value":"miroiterie","count":1},{"value":"Mercerie","count":1},{"value":"Location de matériel BTP","count":1},{"value":"Piscines et spas","count":1},{"value":"Matériaux de construction","count":1},{"value":"Location matériel","count":1},{"value":"Transports spéciaux","count":1},{"value":"Machines à coudre","count":1},{"value":"Porcelaine, Art de la Table Japonais & Épicerie Fine Japonaise","count":1},{"value":"Magasin de vente de la Scierie Germain-Mougenot","count":1},{"value":"Vente et installation de récupérateurs d'eau de pluie","count":1},{"value":"Magasin de poêles à granulés","count":1},{"value":"swimming pools ; Piscines","count":1},{"value":"Vente de produits régionaux","count":1},{"value":"Commerce équitable.","count":1},{"value":"machines à coudre","count":1},{"value":"Location de Canoë et parcours guidés","count":1},{"value":"objets connectés pour smartphones et tablettes","count":1},{"value":"Vente réparations de matériels pour quads, motoneiges, fôret, motoculture, parcs et jardins","count":1},{"value":"Volailles, rotisserie, traiteur","count":1},{"value":"vente de mannequins","count":1},{"value":"Service de mise en vente de voitures d'occasion","count":1},{"value":"Vente directe à la ferme","count":1},{"value":"destockage de marques","count":1},{"value":"Location de matériel pour les réceptions","count":1},{"value":"fr:tissus d'habillement & d'ameublement","count":1},{"value":"Mardi 12 septembre, à 9 h 30, le nouveau magasin Photo Flash de La Ferté-Macé (Orne) ouvrira ses portes zone du Parc avec à sa tête Jordan Gigan.","count":1},{"value":"Point d'accueil de transporteur TNT","count":1},{"value":"Spécialités italiennes, pâtes fraiches, pizza, quiches","count":1},{"value":"Charcuterie traiteur","count":1},{"value":"Boucherie","count":1},{"value":"Cordonnerie, clés","count":1},{"value":"Vente d'objets divers pour l'intérieur :Petit mobilier, vaisselle, décorations, etc...Contenu adapté en fonction du calendrier.","count":1},{"value":"vente à la ferme,viande","count":1},{"value":"Concept store végane ! Espace d'information et d'inspiration pour véganes, curieux-ses & personnes bienveillantes.","count":1},{"value":"A shop that create advertising on tee-shirts, flyers, …","count":1},{"value":"Clothing alteration service ","count":1},{"value":"Propose des solutions alternatives et glamour au textile jetable ordinaire avec des marques essentiellement françaises !","count":1},{"value":"Conseil & Gestion de Patrimoine Conseil - Placement - Financement - Immobilier","count":1},{"value":"Artisanat d'art réalisé à partir d'objet recyclés","count":1},{"value":"Épicerie fine","count":1},{"value":"Articles en bois fabrication locale","count":1},{"value":"Dératisation et suppression de nuisibles","count":1},{"value":"Magasin Audio Discount","count":1},{"value":"Magasin de sports, Location de skis, Golf, Tennis","count":1},{"value":"Vente - Réparation - Entretien matériel de jardinage","count":1},{"value":"Imprimerie, travaux graphiques, photocopies, reprographie, impression numérique enseignes, reconditionnement cartouches, publicité, ","count":1},{"value":"Restaurant, Épicerie, Bar","count":1},{"value":"Laden und Begegnungsort für anders Wertiges","count":1},{"value":"Boutique éphémère dont les occupants changent au bout d'une ou deux semaines.","count":1},{"value":"Vente d'imprimantes 3D pour industriels et particuliers, de filaments, de stylos d'impression 3D, de scanners 3D. Formation sur les imprimantes 3D et leur logiciels.","count":1},{"value":"Articles de fête","count":1},{"value":"maconnerie","count":1},{"value":"Achat vente échange livres d'occasion cd DVD","count":1},{"value":"Impression publicitaire sur tous supports, textile, publicité adhésive.","count":1},{"value":"Deguisement ; articles de fête","count":1},{"value":"Rental","count":1},{"value":"Chaîne de cuisines sur mesure offrant une sélection d’électroménager, mobilier, équipements et accessoires.","count":1},{"value":"Achat or","count":1},{"value":"Rez-de-chaussée en zone départ.\nCasino Shop est ouvert 7 jours sur 7 et vous propose un grand choix de produits frais, de snacking et de produits gourmands !","count":1},{"value":"La boutique Relay propose aux voyageurs un vaste choix de presse française et internationale, du tabac, de la confiserie et encas, des produits de dépannage, ainsi qu'une sélection de jouets et cadeaux.","count":1},{"value":"Vous y trouverez parfums, cosmétiques, alcool, tabac, confiserie, accessoires de voyage et un espace\nentièrement consacré aux produits régionaux. ","count":1},{"value":"Services à domicile pour les personnes âgées ou dépendantes","count":1},{"value":"Magasin d'alimentation biologique","count":1},{"value":"sells books, music, games, comics, travel guides, magazine","count":1},{"value":"Vente d'algues et de produits à base d'algues.","count":1},{"value":"fr:vente, location, réparation de matériel médico-chirurgical","count":1},{"value":"équipement des commerces et des collectivités","count":1},{"value":"Magasin de vente et location de déguisements","count":1},{"value":"Supermarché, vente d'épices, fruits et légumes, boucherie halal, produits orientaux, pain cuit sur place. Horaires d'ouverture : Tout les jours de la semaine (dimanche compris) de 8:30 à 12:00 et de 14:00 à 19:00 .","count":1},{"value":"Location de matériel","count":1},{"value":"fr:drugstore de la coiffure","count":1},{"value":"revente et production d'énergie solaire à EDF","count":1},{"value":"fr:sanitaire, chauffage, climatisation","count":1},{"value":"Piscine et nautique","count":1},{"value":"Articles de bureau destinés aux professionnels. ouvert aux particuliers","count":1},{"value":"Motoculture, serrurerie et métallerie","count":1},{"value":"magasain de prêt à porter","count":1},{"value":"Entreprise horticole","count":1},{"value":"sol - mur - rideaux - peinture","count":1},{"value":"vente d'olives","count":1}],"count":113},{"key":"operator","tags":[{"value":"Total","count":15},{"value":"Avia","count":4},{"value":"Esso","count":3},{"value":"Elan","count":2},{"value":"Shell","count":2},{"value":"E. Leclerc","count":2},{"value":"E. Mulot SAS","count":1},{"value":"Evelyne LAURENT","count":1},{"value":"Vival","count":1},{"value":"sarl","count":1},{"value":"Clear Channel","count":1},{"value":"AGF","count":1},{"value":"Tankstellen Services Sârl","count":1},{"value":"Réseau67","count":1},{"value":"Molimard","count":1},{"value":"APRR","count":1},{"value":"BP","count":1},{"value":"Gaël GUELOU","count":1},{"value":"Carburants Sud Ardèche","count":1},{"value":"EDF","count":1},{"value":"Michèle Scotto","count":1},{"value":"Onglerie","count":1},{"value":"Rastpark Europabrücke","count":1},{"value":"Tryba","count":1},{"value":"New Holland;Promodis","count":1},{"value":"Coudert","count":1},{"value":"Yvon Lecomte","count":1},{"value":"Pierric Jagu","count":1},{"value":"Jean-Luc GREGOIRE","count":1},{"value":"tryba","count":1},{"value":"Maison Ramajo","count":1},{"value":"Queau Vevaform","count":1},{"value":"Minit France","count":1},{"value":"Office de tourisme d'Épinal","count":1},{"value":"Le Canophile","count":1},{"value":"Cornu","count":1},{"value":"Alain Véniel","count":1},{"value":"Christophe Faget","count":1},{"value":"TOTAL","count":1},{"value":"Eueka","count":1},{"value":"Olivier Lepy","count":1},{"value":"Casino","count":1},{"value":"Réseau SOCODA","count":1},{"value":"Claire DEMANGE","count":1},{"value":"Dominique Brochard","count":1},{"value":"Grand Angoulême","count":1},{"value":"Rudy Castelle","count":1},{"value":"Carol & Dominique Taurines","count":1},{"value":"Coopérative Maritime Étaploise","count":1},{"value":"Otis","count":1},{"value":"Eugène Herrero","count":1},{"value":"Thierry Catalano","count":1},{"value":"Adeline Bertrand","count":1},{"value":"Picard Surgelés","count":1},{"value":"Laurent Courtois","count":1},{"value":"Rouget Volailles","count":1},{"value":"PONS","count":1},{"value":"Shiva Groupe","count":1},{"value":"Leclerc","count":1},{"value":"DUCS 64","count":1},{"value":"SARL GGE PAMBRUN","count":1},{"value":"EURL Ferreira","count":1},{"value":"Mr RASCHETTI Fabrice","count":1},{"value":"Thai Vang","count":1},{"value":"STDE","count":1},{"value":"E.Leclerc","count":1},{"value":"Maison Etanche","count":1},{"value":"Babou","count":1},{"value":"La Toque Cuivrée","count":1},{"value":"Stokomani","count":1},{"value":"Co-op","count":1},{"value":"motorcycle part finder","count":1},{"value":"Sandpiper CI","count":1},{"value":"Groupement des Mousquetaires","count":1},{"value":"Noz","count":1},{"value":"Nautic Pêche","count":1},{"value":"La Foir'Fouille","count":1},{"value":"TRB Tankstellen- und Raststätten- Betriebs GmbH","count":1},{"value":"Centrakor","count":1},{"value":"AD Piscines","count":1},{"value":"La Serrurerie Rémoise","count":1},{"value":"SARL Stardec","count":1},{"value":"www.planet-bison.fr","count":1}],"count":105},{"key":"brand","tags":[{"value":"Total","count":19},{"value":"Avia","count":11},{"value":"Esso","count":9},{"value":"Elan","count":6},{"value":"Independent","count":3},{"value":"Shell","count":3},{"value":"BP","count":3},{"value":"Total Access","count":2},{"value":"Q8","count":2},{"value":"Fly","count":2},{"value":"Mondial Piscine","count":1},{"value":"Desigual","count":1},{"value":"Fnac","count":1},{"value":"Camper","count":1},{"value":"GiFi","count":1},{"value":"Kiloutou","count":1},{"value":"Total excellium","count":1},{"value":"Avis;Budget","count":1},{"value":"Aral","count":1},{"value":"Yamaha","count":1},{"value":"BMW","count":1},{"value":"E. Leclerc","count":1},{"value":"veranda","count":1}],"count":73},{"key":"fuel:diesel","tags":[{"value":"yes","count":61}],"count":61},{"key":"note","tags":[{"value":"Maroquinerie","count":2},{"value":"Vacant","count":2},{"value":"veuiller basculer l'ancien commerce en was:name et was:shop","count":2},{"value":"hammam","count":1},{"value":"chauffage sdb clim plomberie","count":1},{"value":"transport","count":1},{"value":"TradiÉco","count":1},{"value":"Vente de linge de maison et broderie","count":1},{"value":"Vente de linge de maison","count":1},{"value":"Vente et réparation de matériel nautique","count":1},{"value":"Vente textile, linge de maison","count":1},{"value":"Tourist Wares/Souvenirs","count":1},{"value":"martial art equipment","count":1},{"value":"Produits locaux, vin, fromage, etc","count":1},{"value":"Vente de miel","count":1},{"value":"Marché Chinois Sushi","count":1},{"value":"Santé Globale propose des services de santé (sur rendez-vous) en naturopathie, aromathérapie, phyothérapie, etc., des produits de santé spécifiques et des formations pour retrouver une santé équilibrée.","count":1},{"value":"Suzy styles [chaussures]","count":1},{"value":"Mailles shop","count":1},{"value":"\"veuiller basculer l'ancien commerce en was:name\"","count":1},{"value":"préciser le type de commerce","count":1},{"value":"équipements de la maison","count":1},{"value":"Location de Vaisselle et de matériel de réception","count":1},{"value":"Vente et réparations de: - 2 roues (motos, scooters), - tondeuses, tronçonneuses","count":1},{"value":"Précédemment: \"Corps Éveillé\"","count":1},{"value":"ébéniste","count":1},{"value":"Object tags should be updated","count":1},{"value":"L'impression 3D est un nouveau monde qui s'ouvre à vous. Dans ce monde c'est votre imagination qui est au pouvoir. Tous les usages de l'impression 3D n'ont pas encore été inventé, à vous de nous surprendre quotidiennement avec vos trouvailles et invention","count":1},{"value":"maroquinerie","count":1},{"value":"Huilerie Artisanal de Noix","count":1},{"value":"Couture, retouche","count":1},{"value":"fermé définitivement","count":1},{"value":"Vente de farine pour particuliers et animaux","count":1},{"value":"a verifier si vacant","count":1},{"value":"Vente de vin, fromage et charcuterie","count":1},{"value":"patissier chocolatier glacier","count":1},{"value":"ateliers de patisserie","count":1},{"value":"trottinettes électriques","count":1},{"value":"Magasin de type entrepôt, situé en rez-de-chaussée, sans étage (voir photo de façade sur le site). L'accès à une personne en fauteuil roulant peut s'avérer un peu délicat : les allées sont peu adaptées pour y circuler en fauteuil.","count":1},{"value":"retoucheur","count":1},{"value":"électronique","count":1},{"value":"Garden machinery, small tractors, mowers etc, sold and repaired","count":1},{"value":"On peut y acheter des forfait de ski pour les remontés mécaniques","count":1},{"value":"Réservé aux professionnels de la coiffure et de l'esthétique","count":1},{"value":"Multiservices : cordonnerie, clé, tampons, gravure, faire part","count":1},{"value":"Spécialiste emballage","count":1},{"value":"vente de cidre, il vaut mieux appeler avant de venir","count":1},{"value":"Magasin de feux d'artifices.","count":1},{"value":"translated","count":1},{"value":"vend materiel pour piscines","count":1},{"value":"Piles et batteries (electrical batteries)","count":1},{"value":"Magasin de fournitures beaux-arts","count":1},{"value":"Fermé","count":1},{"value":"Vente de Tableaux","count":1},{"value":"Loisirs créatifs","count":1},{"value":"Vente de fuel","count":1},{"value":"Société de transports","count":1},{"value":"Coopératives agricoles","count":1}],"count":61},{"key":"level","tags":[{"value":"0","count":50},{"value":"1","count":4},{"value":"-1","count":3},{"value":"2","count":1}],"count":58},{"key":"fixme","tags":[{"value":"shop=?","count":15},{"value":"resurvey","count":5},{"value":"tag","count":5},{"value":"check name, Photo blurred","count":2},{"value":"Add shop name","count":2},{"value":"fuel types","count":1},{"value":"Matériel pour coiffeurs","count":1},{"value":"Il faudrait vérifier le type de magasin.","count":1},{"value":"tags","count":1},{"value":"name, kind of shop","count":1},{"value":"Seems to be clothes, accessories and perfume. Don't know how to make a small shop all of these! and more","count":1},{"value":"Poêle et cheminées","count":1},{"value":"draft","count":1},{"value":"vérifier le type de commerce","count":1},{"value":"tag shop trottinette","count":1},{"value":"Voir le nom","count":1},{"value":"name, photo blurred","count":1},{"value":"Magasin de semelles orthopédiques","count":1},{"value":"name","count":1},{"value":"Vente de batterie, je ne sais pas comment le taguer","count":1},{"value":"Fait ! Vérifier le nom : name renseigné en 2011, alt_name d'après Finess 2014","count":1},{"value":"completer le tag shop","count":1},{"value":"shop type","count":1}],"count":47},{"key":"indoor","tags":[{"value":"room","count":28},{"value":"yes","count":10},{"value":"area","count":7}],"count":45},{"key":"craft","tags":[{"value":"yes","count":8},{"value":"shoemaker","count":4},{"value":"plumber","count":2},{"value":"jeweller","count":2},{"value":"sculptor","count":2},{"value":"window_construction","count":2},{"value":"brewery","count":1},{"value":"pottery","count":1},{"value":"sun_protection","count":1},{"value":"metal_construction","count":1},{"value":"roofer","count":1},{"value":"hvac","count":1},{"value":"caterer","count":1},{"value":"handicraft","count":1},{"value":"key_cutter","count":1},{"value":"agricultural_engines","count":1},{"value":"blacksmith","count":1},{"value":"weaver","count":1},{"value":"upholsterer","count":1},{"value":"soap_maker","count":1},{"value":"ceramic","count":1},{"value":"tiler","count":1},{"value":"joiner","count":1},{"value":"swimming_pool","count":1},{"value":"bakery","count":1},{"value":"stand_builder","count":1},{"value":"painter","count":1},{"value":"sound_system","count":1},{"value":"heating_engineer","count":1},{"value":"house_building","count":1},{"value":"locksmith","count":1}],"count":45},{"key":"email","tags":[{"value":"contact@monboudoirbobo.com","count":1},{"value":"contact@leschampsduverdet.fr","count":1},{"value":"kabouca@gmail.com","count":1},{"value":"adm.caen@wanadoo.fr","count":1},{"value":"manzoni-freres@wanadoo.fr","count":1},{"value":"info@laboutiqueduchampignon","count":1},{"value":"contact@savonduchaudron.com","count":1},{"value":"girouette@jouvenaud.com","count":1},{"value":"lecomte@terre-verre.fr","count":1},{"value":"sophiepinard@hotmail.fr","count":1},{"value":"contact@laptiteflam.com","count":1},{"value":"bernard.guillemin56@orange.fr","count":1},{"value":"info@conceptstore3D.com","count":1},{"value":"contact@ideesbois.net","count":1},{"value":"lionel.martin88@orange.fr","count":1},{"value":"saslpag@free.fr","count":1},{"value":"la.boutique.du.lac@gmail.com","count":1},{"value":"sm.pierrel@wanadoo.fr","count":1},{"value":"info@huilerie-batard.com","count":1},{"value":"cannes@agenceauto.com","count":1},{"value":"beaune@rexel.fr","count":1},{"value":"audio2000.agora@sfr.fr","count":1},{"value":"http://www.forumplus.fr/fr/contact.php","count":1},{"value":"hello@aujourdhui-demain.com","count":1},{"value":"onfit.boutique@gmail.com","count":1},{"value":"la-boutique-de-l-emballage@orange.fr","count":1},{"value":"boutiquebbco@sfr.fr","count":1},{"value":"rennes@dietplus.fr","count":1},{"value":"boutique-laboheme@laposte.net","count":1},{"value":"info@mauduitsports.com","count":1},{"value":"at2e@bbox.fr","count":1},{"value":"maisonduvelo@pays-epinal.fr","count":1},{"value":"cloches.obertino.c@orange.fr","count":1},{"value":"courtois_laurent@orange.fr","count":1},{"value":"contact@batteries76.com","count":1},{"value":"contact@integralpeche.fr","count":1},{"value":"hyperpleinciel-neufchateau@orange.fr","count":1}],"count":37},{"key":"ref:FR:prix-carburants","tags":[{"value":"89000007","count":1},{"value":"89200008","count":1},{"value":"56109001","count":1},{"value":"21800009","count":1},{"value":"14700007","count":1},{"value":"17200009","count":1},{"value":"29200016","count":1},{"value":"10110001","count":1},{"value":"6560005","count":1},{"value":"35750002","count":1},{"value":"56250004","count":1},{"value":"35590004","count":1},{"value":"13009005","count":1},{"value":"56430002","count":1},{"value":"77820003","count":1},{"value":"13005013","count":1},{"value":"63540002","count":1},{"value":"89380006","count":1},{"value":"56450002","count":1},{"value":"89600003","count":1},{"value":"10600009","count":1},{"value":"5100001","count":1},{"value":"69600004","count":1},{"value":"31100010","count":1},{"value":"85000010","count":1},{"value":"73000007","count":1},{"value":"91640004","count":1},{"value":"91540003","count":1},{"value":"29900003","count":1},{"value":"52100004","count":1},{"value":"42110006","count":1},{"value":"89000004","count":1},{"value":"10200004","count":1},{"value":"7170001","count":1},{"value":"76480001","count":1},{"value":"21490003","count":1}],"count":36},{"key":"ref:FR:SIRET","tags":[{"value":"?","count":5},{"value":"34417667200485","count":1},{"value":"79055723500013","count":1},{"value":"40877210100858","count":1},{"value":"514 075 316 00018","count":1},{"value":"378 180 822 00017","count":1},{"value":"793 405 275 00017","count":1},{"value":"779 761 964 00013","count":1},{"value":"519 369 656 00011","count":1},{"value":"485 026 454 00010","count":1},{"value":"50 142 113 00041","count":1},{"value":"81278445200029","count":1},{"value":"39330103100018","count":1},{"value":"82243849500027","count":1},{"value":"48087992300013","count":1},{"value":"493923825","count":1},{"value":"44079801500010","count":1},{"value":"41179635200010","count":1},{"value":"42442171700036","count":1},{"value":"57214188501950","count":1},{"value":"33842346000025","count":1},{"value":"53970036900017","count":1},{"value":"45268360000012","count":1},{"value":"42511559900010","count":1},{"value":"33088267100036","count":1},{"value":"81322313800013","count":1},{"value":"42206926000020","count":1},{"value":"42291198200037","count":1},{"value":"45170350800015","count":1}],"count":33},{"key":"survey:date","tags":[{"value":"2017-07-28","count":2},{"value":"2018-05-01","count":2},{"value":"2019-04-15","count":2},{"value":"2018-09-21","count":2},{"value":"2017-06-27","count":1},{"value":"2018-05-18","count":1},{"value":"2018-12-05","count":1},{"value":"2017-07-30","count":1},{"value":"2017-12-24","count":1},{"value":"2017-07-01","count":1},{"value":"2017-07-19","count":1},{"value":"2017-07-07","count":1},{"value":"2017-09-29","count":1},{"value":"2018-01-01","count":1},{"value":"2018-10-07","count":1},{"value":"28/5/2015","count":1},{"value":"2018-08-20","count":1},{"value":"2018-02-11","count":1},{"value":"2019-05-03","count":1},{"value":"2017-08-19","count":1},{"value":"2018-10-06","count":1},{"value":"2019-02-27","count":1},{"value":"2019-03-01","count":1},{"value":"2015-09-25","count":1},{"value":"2017-06-10","count":1},{"value":"2018-11-02","count":1},{"value":"2016-12-22","count":1},{"value":"2019-03-09","count":1}],"count":32},{"key":"ref:FR:SIREN","tags":[{"value":"?","count":3},{"value":"533 610 812 00034","count":1},{"value":"408772101","count":1},{"value":"318 100 443 00031","count":1},{"value":"453 573 883 00015","count":1},{"value":"789 303 492 00019","count":1},{"value":"753 609 296 00011","count":1},{"value":"519 887 202 00017","count":1},{"value":"341 086 668 00017","count":1},{"value":"414 885 871 00049","count":1},{"value":"347 761 579 00015","count":1},{"value":"529 221 079 00963","count":1},{"value":"503 808 883 00014","count":1},{"value":"49392382500027","count":1},{"value":"480879923","count":1},{"value":"819 270 679 00015","count":1},{"value":"345 029 474 00110","count":1},{"value":"539700369","count":1},{"value":"452683600","count":1},{"value":"425115599","count":1},{"value":"330882671","count":1},{"value":"813223138","count":1},{"value":"422069260","count":1},{"value":"422911982","count":1},{"value":"344176672","count":1}],"count":27},{"key":"room","tags":[{"value":"shop","count":19},{"value":"yes","count":2}],"count":21},{"key":"landuse","tags":[{"value":"residential","count":14},{"value":"commercial","count":2},{"value":"retail","count":1},{"value":"recreation_ground","count":1},{"value":"tourism","count":1},{"value":"plant_nursery","count":1}],"count":20},{"key":"wall","tags":[{"value":"no","count":20}],"count":20},{"key":"payment:cash","tags":[{"value":"yes","count":19}],"count":19},{"key":"fax","tags":[{"value":"+33 2 96 44 45 78","count":1},{"value":"+33 5 49 51 37 02","count":1},{"value":"+33 3 29 60 84 16","count":1},{"value":"+33 3 29 24 28 40","count":1},{"value":"+33 3 29 25 43 31","count":1},{"value":"+33 3 29 25 66 82","count":1},{"value":"+33 2 99 31 48 82","count":1},{"value":"+33 3 86 71 69 59","count":1},{"value":"+33380227645","count":1},{"value":"+33 9 59 95 02 44","count":1},{"value":"+33 2 33 64 73 16","count":1},{"value":"+33559803526","count":1},{"value":"+33 3 29287069","count":1},{"value":"+33 2 32 08 06 95","count":1},{"value":"+33320553671","count":1},{"value":"08.11.48.18.24","count":1},{"value":"yes","count":1},{"value":"+33 5 56 13 09 33","count":1}],"count":18},{"key":"payment:credit_cards","tags":[{"value":"yes","count":15}],"count":15},{"key":"residential","tags":[{"value":"historic","count":14}],"count":14},{"key":"CLC:year","tags":[{"value":"2006","count":14}],"count":14},{"key":"CLC:code","tags":[{"value":"111","count":14}],"count":14},{"key":"fuel:lpg","tags":[{"value":"yes","count":10},{"value":"no","count":2}],"count":12},{"key":"cuisine","tags":[{"value":"french","count":4},{"value":"pizza","count":2},{"value":"ice_cream","count":1},{"value":"asian","count":1},{"value":"kebab","count":1},{"value":"regional","count":1},{"value":"african","count":1},{"value":"italian","count":1}],"count":12},{"key":"mapillary","tags":[{"value":"FT8hF4-A0U_Lm5BhnzIQbQ","count":1},{"value":"wx4ZbRhPjqsrZrBthqf9XA","count":1},{"value":"GPntoK1x3jaDbEQilp3SnQ","count":1},{"value":"iuUsTvsukIRBcyVnsmXDLQ","count":1},{"value":"swFzNH9x2X2VWMsQORidAA","count":1},{"value":"90nBwo-OXKfXyW4BVZ1e0w","count":1},{"value":"oddECZILlMd3rHMDKJA_fg","count":1},{"value":"jX2RRUEfyupiIhqJjSGyug","count":1},{"value":"IzYRGbrNDUL99EO7c0tQog","count":1}],"count":9},{"key":"wikidata","tags":[{"value":"Q3058173","count":3},{"value":"Q2877946","count":2},{"value":"Q3221668","count":1},{"value":"Q22924787","count":1},{"value":"Q22925048","count":1}],"count":8},{"key":"type:FR:APE","tags":[{"value":"47.52A","count":1},{"value":"10.71A","count":1},{"value":"43.32B","count":1},{"value":"73.11Z","count":1},{"value":"43.34Z","count":1},{"value":"47.78C","count":1},{"value":"43.22B","count":1},{"value":"41.20A","count":1}],"count":8},{"key":"brand:wikipedia","tags":[{"value":"fr:Mister Minit","count":3},{"value":"fr:Espace culturel E. Leclerc","count":2},{"value":"fr:Fnac","count":1},{"value":"fr:Nature et Découvertes","count":1},{"value":"fr:E.Leclerc","count":1}],"count":8},{"key":"office","tags":[{"value":"estate_agent","count":3},{"value":"company","count":2},{"value":"telecommunication","count":1},{"value":"yes","count":1},{"value":"auctioneer","count":1}],"count":8},{"key":"ref:FR:NAF","tags":[{"value":"4673B","count":2},{"value":"5630Z","count":1},{"value":"7211Z","count":1},{"value":"4661Z","count":1},{"value":"4774Z","count":1},{"value":"4645Z","count":1}],"count":7},{"key":"tourism","tags":[{"value":"attraction","count":3},{"value":"museum","count":2},{"value":"camp_site","count":1},{"value":"guest_house","count":1}],"count":7},{"key":"vending","tags":[{"value":"fuel","count":6},{"value":"public_transport_tickets","count":1}],"count":7},{"key":"vending_machine","tags":[{"value":"fuel","count":6}],"count":6},{"key":"entrance","tags":[{"value":"yes","count":4},{"value":"main","count":2}],"count":6},{"key":"wikipedia","tags":[{"value":"fr:Espace culturel E. Leclerc","count":3},{"value":"fr:Babou","count":2},{"value":"fr:Le Comptoir Irlandais","count":1}],"count":6},{"key":"is_in","tags":[{"value":"AVALLON","count":1},{"value":"THEIX","count":1},{"value":"LORIENT","count":1},{"value":"ZI des Crémades","count":1},{"value":"A-10","count":1},{"value":"FEURS","count":1}],"count":6},{"key":"leisure","tags":[{"value":"sports_centre","count":2},{"value":"trampoline_park","count":1},{"value":"amusement_arcade","count":1},{"value":"garden","count":1}],"count":5},{"key":"sport","tags":[{"value":"free_flying","count":2},{"value":"laser_tag","count":2},{"value":"canoe;kayak","count":1}],"count":5},{"key":"created_by","tags":[{"value":"iLOE 1.9","count":5}],"count":5},{"key":"clothes","tags":[{"value":"women","count":1},{"value":"sports","count":1},{"value":"women;fashion","count":1},{"value":"women;men","count":1},{"value":"food;oil;sauce","count":1}],"count":5},{"key":"payment:debit_cards","tags":[{"value":"yes","count":5}],"count":5},{"key":"brand:wikidata","tags":[{"value":"Q1389184","count":2},{"value":"Q676585","count":1},{"value":"Q3105439","count":1},{"value":"Q1273376","count":1}],"count":5},{"key":"compressed_air","tags":[{"value":"yes","count":5}],"count":5},{"key":"vacant","tags":[{"value":"yes","count":4}],"count":4},{"key":"hgv:lanes","tags":[{"value":"yes","count":4}],"count":4},{"key":"type","tags":[{"value":"multipolygon","count":3},{"value":"patissier","count":1}],"count":4},{"key":"payment:coins","tags":[{"value":"yes","count":4}],"count":4},{"key":"payment:mastercard","tags":[{"value":"yes","count":4}],"count":4},{"key":"rental","tags":[{"value":"ski","count":4}],"count":4},{"key":"organic","tags":[{"value":"only","count":2},{"value":"yes","count":2}],"count":4},{"key":"area","tags":[{"value":"yes","count":3},{"value":"shop","count":1}],"count":4},{"key":"tobacco","tags":[{"value":"yes","count":4}],"count":4},{"key":"highway","tags":[{"value":"bus_stop","count":2},{"value":"services","count":2}],"count":4},{"key":"internet_access","tags":[{"value":"terminal","count":2},{"value":"yes","count":1},{"value":"wlan","count":1}],"count":4},{"key":"payment:visa","tags":[{"value":"yes","count":4}],"count":4},{"key":"healthcare","tags":[{"value":"nutrition_counselling","count":2},{"value":"physiotherapist","count":1},{"value":"laboratory","count":1}],"count":4},{"key":"healthcare:speciality","tags":[{"value":"nutrition","count":2},{"value":"biology","count":1},{"value":"aromatherapy","count":1}],"count":4},{"key":"layer","tags":[{"value":"1","count":2},{"value":"-1","count":2}],"count":4},{"key":"roof:levels","tags":[{"value":"1","count":3}],"count":3},{"key":"roof:shape","tags":[{"value":"many","count":1},{"value":"gabled","count":1},{"value":"flat","count":1}],"count":3},{"key":"toilets","tags":[{"value":"yes","count":3}],"count":3},{"key":"fuel:HGV_diesel","tags":[{"value":"yes","count":3}],"count":3},{"key":"ref:FR:FINESS","tags":[{"value":"060017225","count":1},{"value":"380017236","count":1},{"value":"590013801","count":1}],"count":3},{"key":"was:shop","tags":[{"value":"clothes","count":2},{"value":"interior_decoration;clothes","count":1}],"count":3},{"key":"takeaway","tags":[{"value":"only","count":2},{"value":"yes","count":1}],"count":3},{"key":"fuel:biodiesel","tags":[{"value":"yes","count":2},{"value":"no","count":1}],"count":3},{"key":"old_shop","tags":[{"value":"clothes","count":1},{"value":"interior_decoration","count":1},{"value":"second_hand","count":1}],"count":3},{"key":"second_hand","tags":[{"value":"yes","count":2},{"value":"only","count":1}],"count":3},{"key":"smoking","tags":[{"value":"no","count":3}],"count":3},{"key":"ref:FR:CRTA","tags":[{"value":"RESAQU064V54PB2E","count":1},{"value":"PCUAQU064FS000C3","count":1}],"count":2},{"key":"fair_trade","tags":[{"value":"only","count":1},{"value":"yes","count":1}],"count":2},{"key":"payment:cheque","tags":[{"value":"yes","count":2}],"count":2},{"key":"fuel:GTL_diesel","tags":[{"value":"yes","count":2}],"count":2},{"key":"disused:shop","tags":[{"value":"clothes","count":1},{"value":"yes","count":1}],"count":2},{"key":"label","tags":[{"value":"Accueil Vélo","count":2}],"count":2},{"key":"entrance:step_count","tags":[{"value":"0","count":2}],"count":2},{"key":"entrance:step:height","tags":[{"value":"0","count":2}],"count":2},{"key":"entrance:width","tags":[{"value":"2.1","count":1},{"value":"1.7","count":1}],"count":2},{"key":"animal","tags":[{"value":"wellness","count":2}],"count":2},{"key":"origin","tags":[{"value":"british","count":1},{"value":"madagascar","count":1}],"count":2},{"key":"restaurant","tags":[{"value":"yes","count":2}],"count":2},{"key":"capacity:truck_diesel_pumps","tags":[{"value":"4","count":1},{"value":"6","count":1}],"count":2},{"key":"start_date","tags":[{"value":"1997","count":1},{"value":"2017-04","count":1}],"count":2},{"key":"payment:notes","tags":[{"value":"yes","count":2}],"count":2},{"key":"delivery","tags":[{"value":"no","count":2}],"count":2},{"key":"capacity:smoker_free","tags":[{"value":"existing","count":2}],"count":2},{"key":"capacity:truck","tags":[{"value":"70","count":1},{"value":"120","count":1}],"count":2},{"key":"height","tags":[{"value":"3","count":1},{"value":"10","count":1}],"count":2},{"key":"copier","tags":[{"value":"yes","count":2}],"count":2},{"key":"fast_food","tags":[{"value":"yes","count":2}],"count":2},{"key":"lit","tags":[{"value":"24/7","count":2}],"count":2},{"key":"payment:uta","tags":[{"value":"yes","count":2}],"count":2},{"key":"payment:bancomat","tags":[{"value":"yes","count":2}],"count":2},{"key":"payment:espece","tags":[{"value":"yes","count":2}],"count":2},{"key":"dispensing","tags":[{"value":"yes","count":1}],"count":1},{"key":"payment:euroshell","tags":[{"value":"yes","count":1}],"count":1},{"key":"payment:american_express","tags":[{"value":"yes","count":1}],"count":1},{"key":"tickets:public_transport","tags":[{"value":"yes","count":1}],"count":1},{"key":"shop:de","tags":[{"value":"Antiquitäten","count":1}],"count":1},{"key":"shower","tags":[{"value":"yes","count":1}],"count":1},{"key":"wake_up","tags":[{"value":"yes","count":1}],"count":1},{"key":"washers","tags":[{"value":"yes","count":1}],"count":1},{"key":"drive_through","tags":[{"value":"no","count":1}],"count":1},{"key":"internet_access:fee","tags":[{"value":"no","count":1}],"count":1},{"key":"ref:FR:FANTOIR","tags":[{"value":"884700481T","count":1}],"count":1},{"key":"canoe_rental","tags":[{"value":"yes","count":1}],"count":1},{"key":"club","tags":[{"value":"sport","count":1}],"count":1},{"key":"fee","tags":[{"value":"yes","count":1}],"count":1},{"key":"access","tags":[{"value":"destination","count":1}],"count":1},{"key":"bar","tags":[{"value":"yes","count":1}],"count":1},{"key":"payment:travellers_cheque","tags":[{"value":"yes","count":1}],"count":1},{"key":"service:date","tags":[{"value":"2017","count":1}],"count":1},{"key":"cafe","tags":[{"value":"yes","count":1}],"count":1},{"key":"payment:cash:XLT-DUME","tags":[{"value":"yes","count":1}],"count":1},{"key":"seamark:small_craft_facility:category","tags":[{"value":"bottle_gas;fuel_station;provisions","count":1}],"count":1},{"key":"workshop","tags":[{"value":"fablab","count":1}],"count":1},{"key":"press","tags":[{"value":"yes","count":1}],"count":1},{"key":"pub","tags":[{"value":"yes","count":1}],"count":1},{"key":"was:clothes","tags":[{"value":"women","count":1}],"count":1},{"key":"newspaper","tags":[{"value":"no","count":1}],"count":1},{"key":"mobile_phone:repair","tags":[{"value":"yes","count":1}],"count":1},{"key":"type:FR:FINESS","tags":[{"value":"611","count":1}],"count":1},{"key":"school","tags":[{"value":"yes","count":1}],"count":1},{"key":"ele","tags":[{"value":"1450 M","count":1}],"count":1},{"key":"greeting_cards","tags":[{"value":"yes","count":1}],"count":1},{"key":"payment:phone","tags":[{"value":"yes","count":1}],"count":1},{"key":"service","tags":[{"value":"repair","count":1}],"count":1},{"key":"payment:cartes_bleues","tags":[{"value":"yes","count":1}],"count":1},{"key":"diet:vegan","tags":[{"value":"only","count":1}],"count":1},{"key":"cabins","tags":[{"value":"yes","count":1}],"count":1},{"key":"caravans","tags":[{"value":"yes","count":1}],"count":1},{"key":"openfire","tags":[{"value":"no","count":1}],"count":1},{"key":"tents","tags":[{"value":"yes","count":1}],"count":1},{"key":"gift","tags":[{"value":"yes","count":1}],"count":1},{"key":"ski:rental","tags":[{"value":"yes","count":1}],"count":1},{"key":"atm","tags":[{"value":"yes","count":1}],"count":1},{"key":"bench","tags":[{"value":"yes","count":1}],"count":1},{"key":"payment:diners_club","tags":[{"value":"yes","count":1}],"count":1},{"key":"produce","tags":[{"value":"seafood;algae","count":1}],"count":1},{"key":"FIXME","tags":[{"value":"Laboratoire d'Analyses Médicales","count":1}],"count":1},{"key":"public_transport","tags":[{"value":"platform","count":1}],"count":1},{"key":"advertising","tags":[{"value":"poster_box","count":1}],"count":1},{"key":"bakery","tags":[{"value":"yes","count":1}],"count":1},{"key":"luminous","tags":[{"value":"yes","count":1}],"count":1},{"key":"newsagent","tags":[{"value":"yes","count":1}],"count":1},{"key":"heritage:operator","tags":[{"value":"mhs","count":1}],"count":1},{"key":"historic","tags":[{"value":"house","count":1}],"count":1},{"key":"mhs:inscription_date","tags":[{"value":"1926","count":1}],"count":1},{"key":"ref:mhs","tags":[{"value":"PA00089269","count":1}],"count":1},{"key":"capacity:persons","tags":[{"value":"70","count":1}],"count":1},{"key":"FR:ERP","tags":[{"value":"M-5","count":1}],"count":1},{"key":"url","tags":[{"value":"http://www.bleulibellule.com/magasin/orange.html","count":1}],"count":1},{"key":"shelter","tags":[{"value":"yes","count":1}],"count":1},{"key":"network","tags":[{"value":"Divia","count":1}],"count":1},{"key":"fuel:diesel_B","tags":[{"value":"yes","count":1}],"count":1},{"key":"is_in:province","tags":[{"value":"GUIPÚZCOA","count":1}],"count":1},{"key":"outdoor_seating","tags":[{"value":"yes","count":1}],"count":1},{"key":"faces","tags":[{"value":"2","count":1}],"count":1},{"key":"comment","tags":[{"value":"fuel types can be improve","count":1}],"count":1},{"key":"barrier","tags":[{"value":"wall","count":1}],"count":1},{"key":"disused:amenity","tags":[{"value":"fuel","count":1}],"count":1},{"key":"shop:fr","tags":[{"value":"Ebénesterie","count":1}],"count":1},{"key":"baby_change","tags":[{"value":"yes","count":1}],"count":1},{"key":"capacity:restaurant","tags":[{"value":"148","count":1}],"count":1},{"key":"capacity:shower","tags":[{"value":"4","count":1}],"count":1},{"key":"capacity:toilets","tags":[{"value":"6","count":1}],"count":1},{"key":"payment:dkv","tags":[{"value":"yes","count":1}],"count":1},{"key":"payment:ec","tags":[{"value":"yes","count":1}],"count":1},{"key":"playground","tags":[{"value":"yes","count":1}],"count":1},{"key":"tv","tags":[{"value":"yes","count":1}],"count":1},{"key":"bus","tags":[{"value":"yes","count":1}],"count":1},{"key":"wheelchair:entrance_width","tags":[{"value":"120","count":1}],"count":1},{"key":"grooming","tags":[{"value":"yes","count":1}],"count":1},{"key":"place","tags":[{"value":"isolated_dwelling","count":1}],"count":1},{"key":"payment:cheques","tags":[{"value":"yes","count":1}],"count":1},{"key":"map","tags":[{"value":"mapnik","count":1}],"count":1},{"key":"old_ref:FR:NAF","tags":[{"value":"4771Z","count":1}],"count":1},{"key":"old_ref:FR:SIRET","tags":[{"value":"41315173905475","count":1}],"count":1},{"key":"old_website","tags":[{"value":"http://www.lahalle.com/","count":1}],"count":1},{"key":"old_wikipedia","tags":[{"value":"fr:La Halle","count":1}],"count":1},{"key":"was:description","tags":[{"value":"fr:magasin de vêtements","count":1}],"count":1}]