[{"key":"amenity","tags":[{"value":"baking_oven","count":142}],"count":142},{"key":"oven","tags":[{"value":"wood_fired","count":35},{"value":"bread","count":1}],"count":36},{"key":"historic","tags":[{"value":"yes","count":13},{"value":"oven","count":1}],"count":14},{"key":"access","tags":[{"value":"private","count":7},{"value":"yes","count":2},{"value":"permissive","count":2}],"count":11},{"key":"wall","tags":[{"value":"no","count":3}],"count":3},{"key":"description","tags":[{"value":"Atelier et four à pain de paysans-boulangers biologiques. Organic farmers/bakers' bread oven and workshop.","count":1},{"value":"Communal, fermé à clef","count":1},{"value":"Bread oven","count":1}],"count":3},{"key":"start_date","tags":[{"value":"1867","count":1},{"value":"1838","count":1},{"value":"1786","count":1}],"count":3},{"key":"tourism","tags":[{"value":"attraction","count":2},{"value":"yes","count":1}],"count":3},{"key":"operator","tags":[{"value":"Le Ti Fournil","count":1},{"value":"comité des fêtes Lizio","count":1}],"count":2},{"key":"website","tags":[{"value":"http://letifournil.fr","count":1}],"count":1},{"key":"disused","tags":[{"value":"yes","count":1}],"count":1},{"key":"email","tags":[{"value":"letifournil@letifournil.fr","count":1}],"count":1},{"key":"wikipedia","tags":[{"value":"fr:Four à pain","count":1}],"count":1},{"key":"phone","tags":[{"value":"+33767341013","count":1}],"count":1},{"key":"wikidata","tags":[{"value":"Q798436","count":1}],"count":1},{"key":"layer","tags":[{"value":"-1","count":1}],"count":1},{"key":"energy","tags":[{"value":"wood","count":1}],"count":1},{"key":"fee","tags":[{"value":"no","count":1}],"count":1},{"key":"ruins","tags":[{"value":"yes","count":1}],"count":1},{"key":"mapillary","tags":[{"value":"https://www.mapillary.com/map/im/5_AwNDjzvwmu54vvfOO1Kg","count":1}],"count":1}]