[{"key":"amenity","tags":[{"value":"compressed_air","count":287}],"count":287},{"key":"fee","tags":[{"value":"no","count":91},{"value":"yes","count":29}],"count":120},{"key":"valves","tags":[{"value":"schrader","count":13},{"value":"schrader;presta","count":7},{"value":"presta;schrader","count":3},{"value":"dunlop;regina;schrader;sclaverand","count":2},{"value":"presta;schrader;dunlop","count":1},{"value":"schrader;sclaverand","count":1},{"value":"schrader;presta;dunlop","count":1},{"value":"dunlop;schrader;sclaverand","count":1}],"count":29},{"key":"operator","tags":[{"value":"Métropole du Grand Nancy","count":5},{"value":"washop","count":4},{"value":"Michelin","count":1},{"value":"Azur Lavage Services","count":1},{"value":"E. Leclerc","count":1},{"value":"Total Access","count":1},{"value":"AltaO'","count":1},{"value":"Auchan","count":1},{"value":"Leclerc","count":1},{"value":"lOrient","count":1},{"value":"Avia","count":1},{"value":"Mairie de Montreuil","count":1},{"value":"bp","count":1}],"count":20},{"key":"access","tags":[{"value":"yes","count":13},{"value":"permissive","count":3},{"value":"public","count":1},{"value":"private","count":1}],"count":18},{"key":"service:bicycle:pump","tags":[{"value":"yes","count":16}],"count":16},{"key":"manometer","tags":[{"value":"yes","count":10}],"count":10},{"key":"compressed_air","tags":[{"value":"yes","count":9},{"value":"bicycles","count":1}],"count":10},{"key":"pressure","tags":[{"value":"10","count":8},{"value":"6","count":2}],"count":10},{"key":"compressed_air:fee","tags":[{"value":"no","count":6}],"count":6},{"key":"description","tags":[{"value":"Lavage et gonflage de vélo, retrait de jetons en mairie","count":1},{"value":"Pression des pneus","count":1},{"value":"Nécessite 1€ pour fonctionner","count":1},{"value":"Pour vélos","count":1},{"value":"1€ pour 5 minutes","count":1}],"count":5},{"key":"self_service","tags":[{"value":"yes","count":5}],"count":5},{"key":"compressed_air:manometer","tags":[{"value":"yes","count":5}],"count":5},{"key":"lit","tags":[{"value":"yes","count":2},{"value":"no","count":2}],"count":4},{"key":"payment:coins","tags":[{"value":"yes","count":3},{"value":"0.50€","count":1}],"count":4},{"key":"automated","tags":[{"value":"no","count":4}],"count":4},{"key":"wheelchair","tags":[{"value":"yes","count":4}],"count":4},{"key":"note","tags":[{"value":"vérifier si bicycle_repair_station","count":1},{"value":"doesn't work, needs repair","count":1},{"value":"bycicle station","count":1}],"count":3},{"key":"free","tags":[{"value":"yes","count":1},{"value":"no","count":1}],"count":2},{"key":"level","tags":[{"value":"0","count":1},{"value":"-1","count":1}],"count":2},{"key":"brand","tags":[{"value":"Altao","count":1},{"value":"Altinnova","count":1}],"count":2},{"key":"fixme","tags":[{"value":"Position approximative","count":1},{"value":"fee?","count":1}],"count":2},{"key":"shop","tags":[{"value":"bicycle","count":1}],"count":1},{"key":"location","tags":[{"value":"underground","count":1}],"count":1},{"key":"colour","tags":[{"value":"blue","count":1}],"count":1},{"key":"bicycle","tags":[{"value":"only","count":1}],"count":1},{"key":"wall","tags":[{"value":"no","count":1}],"count":1},{"key":"office","tags":[{"value":"it","count":1}],"count":1},{"key":"mapillary","tags":[{"value":"q_wz9ucMD7txRpmsMaR9Qw","count":1}],"count":1},{"key":"payment:tokens","tags":[{"value":"yes","count":1}],"count":1},{"key":"car","tags":[{"value":"yes","count":1}],"count":1},{"key":"service:bicycle:cleaning","tags":[{"value":"yes","count":1}],"count":1},{"key":"survey:date","tags":[{"value":"2018-10-19","count":1}],"count":1},{"key":"motor_vehicle","tags":[{"value":"no","count":1}],"count":1},{"key":"phone","tags":[{"value":"+33 5 46 67 31 32","count":1}],"count":1},{"key":"website","tags":[{"value":"http://www.chiasson.fr/","count":1}],"count":1}]