[{"key":"location","tags":[{"value":"green","count":2}],"count":2},{"key":"man_made","tags":[{"value":"street_c","count":2}],"count":2},{"key":"operator","tags":[{"value":"Enedis","count":2}],"count":2},{"key":"power","tags":[{"value":"substation","count":2}],"count":2},{"key":"street_cabinet","tags":[{"value":"power","count":2}],"count":2},{"key":"substation","tags":[{"value":"minor_distribution","count":2}],"count":2},{"key":"voltage:primary","tags":[{"value":"20000","count":2}],"count":2},{"key":"voltage:secondary","tags":[{"value":"400","count":2}],"count":2},{"key":"transformer","tags":[{"value":"distribution","count":1}],"count":1}]